verilog_practice_tasks/comb-seq/FSM/src/rx.v
module receiver_state(
    input wire valid_i,
    input wire [4:0] data_i,
    input wire busy,
    output reg ready_o,
    input wire clk
);
reg [4:0] data_s; 
always @(posedge clk) begin
     if(valid_i && ~busy) begin
        ready_o <= 1;
        data_s = data_i;
    end
end
always @(*) begin
    if (valid_i && busy) begin 
        ready_o =  0;
        data_s = 0;
        end
    else begin
        ready_o = 0;
        data_s = 0;
    end
end

endmodule

verilog_practice_tasks/comb-seq/FSM/src/tx.v
module transmission_state(
    input wire clk,
    input wire rst,
    input wire ready_i,
    input wire tx,
    input wire [4:0] data,
    output reg valid_o,
    output reg [4:0] data_o
);
localparam idle = 2'b00;
localparam TX = 2'b01;
localparam valid = 2'b10;
reg [1:0] state;
reg [1:0] next_state;


always @(posedge clk or negedge rst) begin
    if(~rst) begin
        state <= idle;
    end
    else begin
        state <= next_state;
    end
end

always @(*) begin
    case (state)
        idle: begin
            valid_o = 0;
            next_state = TX;
        end
        TX: begin
            valid_o = 0;
            next_state = (tx) ? valid : TX; 
        end
        valid: begin
            valid_o = 1;
            data_o = data;
            next_state = (ready_i) ? TX : valid;
        end
    endcase
end
endmodule

verilog_practice_tasks/comb-seq/FSM/src/fsm.v
module FSM(
    input wire  clk,
    input wire  rst,
    input wire busy,
    input wire tx,
    input wire [4:0] data
);

wire a;
wire b;
wire [4:0] c;


transmission_state u_transmission_state(
    .clk(clk),
    .rst(rst),
    .tx(tx),
    .ready_i(a),
    .data(data),
    .valid_o(b),
    .data_o(c)
);

receiver_state u_receiver_state(
    .valid_i(b),
    .data_i(c),
    .busy(busy),
    .ready_o(a),
    .clk(clk)
);

endmodule

verilog_practice_tasks/comb-seq/FSM/tb/fsm_tb.v
module FSM_tb();
    reg clk;
    reg reset;
    reg busy;
    reg tx;
    reg [4:0]data;
    wire [4:0]data_s;

FSM u_FSM(
    .clk(clk),
    .rst(reset),
    .busy(busy),
    .tx(tx),
    .data(data)
);

always begin
    #5 clk = ~clk;
end

initial begin
    busy = 0;
    clk = 0;
    reset = 1;
    data = 5'b00010;
    tx = 0;
    #5;
    reset = 0;
    #5;
    reset = 1;
    #5;
    tx=1;
    #20;
    tx=0;
    busy=1;
    #10;
    busy=0;
    #100;
    $finish;
end

initial begin
    $dumpfile("temp/fsm.vcd");
    $dumpvars(0,FSM_tb);
end

endmodule

verilog_practice_tasks/comb-seq/FSM/temp/fsm.vcd
$date
	Sat Oct  5 22:13:33 2024
$end
$version
	Icarus Verilog
$end
$timescale
	1s
$end
$scope module FSM_tb $end
$var reg 1 ! busy $end
$var reg 1 " clk $end
$var reg 5 # data [4:0] $end
$var reg 1 $ reset $end
$var reg 1 % tx $end
$scope module u_FSM $end
$var wire 1 ! busy $end
$var wire 1 " clk $end
$var wire 5 & data [4:0] $end
$var wire 1 $ rst $end
$var wire 1 % tx $end
$var wire 5 ' c [4:0] $end
$var wire 1 ( b $end
$var wire 1 ) a $end
$scope module u_receiver_state $end
$var wire 1 ! busy $end
$var wire 1 " clk $end
$var wire 1 ( valid_i $end
$var wire 5 * data_i [4:0] $end
$var reg 5 + data_s [4:0] $end
$var reg 1 ) ready_o $end
$upscope $end
$scope module u_transmission_state $end
$var wire 1 " clk $end
$var wire 5 , data [4:0] $end
$var wire 1 ) ready_i $end
$var wire 1 $ rst $end
$var wire 1 % tx $end
$var parameter 2 - TX $end
$var parameter 2 . idle $end
$var parameter 2 / valid $end
$var reg 5 0 data_o [4:0] $end
$var reg 2 1 next_state [1:0] $end
$var reg 2 2 state [1:0] $end
$var reg 1 ( valid_o $end
$upscope $end
$upscope $end
$upscope $end
$enddefinitions $end
$comment Show the parameter values. $end
$dumpall
b10 /
b0 .
b1 -
$end
#0
$dumpvars
bx 2
bx 1
bx 0
b10 ,
b0 +
bx *
0)
x(
bx '
b10 &
0%
1$
b10 #
0"
0!
$end
#5
b1 1
0(
b0 2
0$
1"
#10
1$
0"
#15
b10 1
b1 2
1%
1"
#20
0"
#25
b10 '
b10 *
b10 0
1(
b10 2
1"
#30
0"
#35
1"
1!
0%
#40
0"
#45
b1 1
1)
b10 +
1"
0!
#50
0"
#55
b0 +
0)
0(
b1 2
1"
