single_cycle_dev/DRAM_4x72/src/dram.v
module DRAM(
    input wire clk,
    input wire reset,
    input [1:0]address,
    input [71:0]dataIN,
    output reg [71:0]dataOUT,
    input wire Write_ReadCOMP
);

reg [71:0] DRAM [3:0];
integer i;

always @(posedge clk) begin
    if(reset) begin
        for (i=0;i<4;i++)
        DRAM[i] = 0;
    end
    else begin 
    if(Write_ReadCOMP) begin 
        DRAM[address] <= dataIN;
    end
    else if(~Write_ReadCOMP) begin 
        dataOUT <= DRAM[address];
    end
    end
end
endmodule

single_cycle_dev/DRAM_4x72/tb/dram_tb.v
module DRAM_tb();
    reg clk;
    reg reset;
    reg [1:0]address;
    reg [71:0]dataIN;
    wire [71:0]dataOUT;
    reg Write_ReadCOMP;

DRAM u_DRAM(
    .clk(clk),
    .reset(reset),
    .address(address),
    .dataIN(dataIN),
    .dataOUT(dataOUT),
    .Write_ReadCOMP(Write_ReadCOMP)
);

always begin
    clk = ~clk;
    #5;
end

initial begin
    clk = 0;
    reset = 1;
    address = 2'b10;
    dataIN = 72'd12;
    Write_ReadCOMP=0;
    #20; 
    reset = 0;
    #5;

    #5;
    Write_ReadCOMP=1;
    #10;
    Write_ReadCOMP=0;
    #100;
    $finish;
end

initial begin
    $dumpfile("temp/dram.vcd");
    $dumpvars(0,DRAM_tb);
end

endmodule

single_cycle_dev/DRAM_4x72/temp/dram.vcd
$date
	Wed Oct 16 14:45:00 2024
$end
$version
	Icarus Verilog
$end
$timescale
	1s
$end
$scope module DRAM_tb $end
$var wire 72 ! dataOUT [71:0] $end
$var reg 1 " Write_ReadCOMP $end
$var reg 2 # address [1:0] $end
$var reg 1 $ clk $end
$var reg 72 % dataIN [71:0] $end
$var reg 1 & reset $end
$scope module u_DRAM $end
$var wire 1 " Write_ReadCOMP $end
$var wire 2 ' address [1:0] $end
$var wire 1 $ clk $end
$var wire 72 ( dataIN [71:0] $end
$var wire 1 & reset $end
$var reg 72 ) dataOUT [71:0] $end
$var integer 32 * i [31:0] $end
$upscope $end
$upscope $end
$enddefinitions $end
#0
$dumpvars
bx *
bx )
b1100 (
b10 '
1&
b1100 %
0$
b10 #
0"
bx !
$end
#5
b100 *
1$
#10
0$
#15
b100 *
1$
#20
0$
0&
#25
b0 !
b0 )
1$
#30
0$
1"
#35
1$
#40
0$
0"
#45
b1100 !
b1100 )
1$
