single_cycle_dev/verilog_zaid/main/src/counter.v
module Counter(
    input wire rst,
    input wire clk,
    output reg [31:0] out
);
    wire [31:0] o;
    assign o = 32'd4;

    always @(posedge clk or posedge rst) begin
        if (rst) 
            out <= 32'b0; 
        else 
            out <= out + o; 
    end
endmodule

single_cycle_dev/verilog_zaid/main/tb/counter_tb.v
module Counter_tb();
    reg rst;
    reg clk;
    wire [31:0]o;

always begin
    #5 clk = ~clk;

end 

Counter u_Counter(
    .rst(rst),
    .clk(clk),
    .out(o)
);

initial begin
        clk = 0;   
        rst = 1;   
        #10 rst = 0; 
        #100;        
        $finish;    
end

initial begin
    $dumpfile("temp/counter.vcd");
    $dumpvars(0,Counter_tb);
end

endmodule

single_cycle_dev/verilog_zaid/main/temp/counter.vcd
$date
	Fri Nov 29 18:05:12 2024
$end
$version
	Icarus Verilog
$end
$timescale
	1s
$end
$scope module Counter_tb $end
$var wire 32 ! o [31:0] $end
$var reg 1 " clk $end
$var reg 1 # rst $end
$scope module u_Counter $end
$var wire 1 " clk $end
$var wire 32 $ o [31:0] $end
$var wire 1 # rst $end
$var reg 32 % out [31:0] $end
$upscope $end
$upscope $end
$enddefinitions $end
#0
$dumpvars
b0 %
b100 $
1#
0"
b0 !
$end
#5
1"
#10
0"
0#
#15
b100 !
b100 %
1"
#20
0"
#25
b1000 !
b1000 %
1"
#30
0"
#35
b1100 !
b1100 %
1"
#40
0"
#45
b10000 !
b10000 %
1"
#50
0"
#55
b10100 !
b10100 %
1"
#60
0"
#65
b11000 !
b11000 %
1"
#70
0"
#75
b11100 !
b11100 %
1"
#80
0"
#85
b100000 !
b100000 %
1"
#90
0"
#95
b100100 !
b100100 %
1"
#100
0"
#105
b101000 !
b101000 %
1"
