single_cycle_dev/verilog_zaid/main/src/data_mem_intf.v
module DMI(
    input wire [31:0]load,
    input wire [5:0]aluOP,
    output reg [31:0]load_data
);
localparam loadByte = 6'd0;
localparam loadHalf = 6'd1;
localparam loadByteUnsigned = 6'd3;
localparam loadHalfUnsigned = 6'd4;
localparam loadWord = 6'd2;

wire [7:0]LB;
wire [15:0]LH;
wire [7:0]LBU;
wire [15:0]LHU;
wire [31:0]LW;

assign LB = load[7:0];
assign LH = load[15:0];
assign LBU = load[7:0];
assign LHU = load[15:0];
assign LW = load[31:0];

always @(*) begin
    case(aluOP)
    loadByte: begin
        load_data = $signed({{24{LB[7]}},LB});
    end
    loadHalf: begin
        load_data = $signed({{16{LH[15]}},LH});
    end
    loadByteUnsigned: begin
        load_data = $unsigned({24'b0,LBU});
    end
    loadHalfUnsigned: begin
        load_data = $unsigned({16'b0, LHU});
    end
    loadWord: begin
        load_data = LW;
    end
    endcase
end

endmodule

single_cycle_dev/verilog_zaid/main/src/RAM.v
module RAM (
    input wire clk,
    input wire [31:0] dataIN,
    input wire [4:0] address, //1 
    input wire readWrite,   //0
    output reg [31:0] dataOUT
);
    reg [31:0] RAM [0:31]; // 32 words of memory

    always @(posedge clk) begin
        if (readWrite) begin
            dataOUT <= RAM[address-1]; // Read   ( i did *address-1* in order for RAM to read same instruction in the next cycle instead of dead reading)
        end else begin
            RAM[address] <= dataIN; // Write
        end
    end
endmodule

single_cycle_dev/verilog_zaid/main/src/alu.v
module alu(
  input wire [31:0]a,
  input wire [31:0]b,
  input wire [5:0]opcode,
  output reg [31:0]c
);

  always @(*) begin
        case(opcode) 
        6'd5: c = a + b;
        6'd6: c = a << b;
        6'd7: c = ($signed(a) < $signed(b)) ? 32'b1 : 32'b0;
        6'd8: c = ($unsigned(a) < $unsigned(b) ) ? 32'b1 : 32'b0;
        6'd9: c = a ^ b;
        6'd10: c = a >> b;
        6'd11: c = a >>> b;
        6'd12: c = a | b;
        6'd13: c = a & b;
        6'd18: c = a + b;
        6'd19: c = a - b;
        6'd20: c = a << b;
        6'd21: c = ($unsigned(a) < $unsigned(b)) ? 32'b1 : 32'b0;
        6'd22: c = ($unsigned(a) < $unsigned(b)) ? 32'b1 : 32'b0;
        6'd23: c = a ^ b; 
        6'd24: c = a >> b; 
        6'd25: c = a >>> b; 
        6'd26: c = a | b;
        6'd27: c = a & b;
        default: c = 32'b0;
        endcase
  end
endmodule

single_cycle_dev/verilog_zaid/main/src/registerfile.v
module register (
    input wire clk,
    input wire reset,
    input wire regWrite, 
    input [31:0] write_data,
    input [4:0] rd_data,
    input [4:0] rs1_data,
    input [4:0] rs2_data,
    output reg [31:0] read_data1,
    output reg [31:0] read_data2
);
    reg [31:0] registerf [0:31];
    integer i;

    // Synchronous
    always @(posedge clk) begin
        if (reset || ~regWrite) begin
            for (i = 0; i < 32; i = i + 1) 
                registerf[i] <= 32'b0; 
        end else if (regWrite && rd_data != 0) begin
            registerf[rd_data] <= write_data; 
        end
    end

    // ASynchronous
    always @(*) begin
        read_data1 = (rs1_data == 0) ? 32'b0 : registerf[rs1_data];
        read_data2 = (rs2_data == 0) ? 32'b0 : registerf[rs2_data];
    end

endmodule

single_cycle_dev/verilog_zaid/main/src/control_decode.v
module ControlDecoder(
    input wire [31:0] instruction,
    output reg [31:0] imm_gen_inst,
    output wire [4:0] rs1,
    output wire [4:0] rs2,
    output wire [4:0] rd,
    output reg regWrite,
    output reg memToReg,
    output reg memWrite,
    output reg operandA,
    output reg operandB,
    output reg branch,
    output reg [5:0] aluOP,
    output reg jalrEN,
    output reg jalEN
);

localparam load_Itype = 7'b0000011;
localparam alu_Itype = 7'b0010011;
localparam jalr_Itype = 7'b1100111;
localparam alu_rtype = 7'b0110011; 

// instr decode
wire [6:0] opcode = instruction[6:0];
wire [2:0] func3 = instruction[14:12];
wire [6:0] func7 = instruction[31:25];
assign rd = instruction[11:7];
assign rs1 = instruction[19:15];
assign rs2 = instruction[24:20];

// Immediate generation logic
always @(*) begin
    case (opcode)
        load_Itype, alu_Itype, jalr_Itype: begin
            imm_gen_inst = {{20{instruction[31]}}, instruction[31:20]};  //Sign extension
        end
        default: begin
            imm_gen_inst = 32'b0;
        end
    endcase
end

// Control decode logic
always @(*) begin
    regWrite = 0;
    memToReg = 0;
    memWrite = 0;
    operandA = 0;
    operandB = 0;
    branch = 0;
    aluOP = 6'd0;
    jalrEN = 0;
    jalEN = 0;

    case (opcode)
        alu_rtype: begin
            case (func3)
                3'd0: aluOP = func7[5] ? 6'd19 : 6'd18;  // SUB or ADD
                3'd1: aluOP = 6'd20;  // SLL
                3'd2: aluOP = 6'd21;  // SLT
                3'd3: aluOP = 6'd22;  // SLTU
                3'd4: aluOP = 6'd23;  // XOR
                3'd5: aluOP = func7[5] ? 6'd25 : 6'd24;  // SRA or SRL
                3'd6: aluOP = 6'd26;  // OR
                3'd7: aluOP = 6'd27;  // AND
            endcase
            regWrite = 1;
        end
        alu_Itype: begin
            case (func3)
                3'd0: aluOP = 6'd5;   // ADDI
                3'd1: aluOP = 6'd6;   // SLLI
                3'd2: aluOP = 6'd7;   // SLTI
                3'd3: aluOP = 6'd8;   // SLTIU
                3'd4: aluOP = 6'd9;   // XORI
                3'd5: aluOP = func7[5] ? 6'd11 : 6'd10;  // SRAI or SRLI
                3'd6: aluOP = 6'd12;  // ORI
                3'd7: aluOP = 6'd13;  // ANDI
            endcase
            regWrite = 1;
            operandA = 1;
        end
        load_Itype: begin
            case (func3)
                3'd0: aluOP = 6'd0;  // LB
                3'd1: aluOP = 6'd1;  // LH
                3'd2: aluOP = 6'd2;  // LW
                3'd3: aluOP = 6'd3;  // LD
                3'd4: aluOP = 6'd4;  // LBU
            endcase
            regWrite = 1;
            memToReg = 1;
            operandA = 1;
        end
        jalr_Itype: begin
            aluOP = 6'd35;  // JALR operation
            regWrite = 1;
            operandA = 1;
        end
    endcase
end

endmodule

single_cycle_dev/verilog_zaid/main/src/counter.v
module Counter(
    input wire rst,
    input wire clk,
    output reg [31:0] out
);
    wire [31:0] o;
    assign o = 32'd4;

    always @(posedge clk or posedge rst) begin
        if (rst) 
            out <= 32'b0; 
        else 
            out <= out + o; 
    end
endmodule

single_cycle_dev/verilog_zaid/main/src/main.v
module MAIN (
    input wire clk,
    input [31:0] dataIN,
    input wire rst,
    input wire en,
    input wire RW
);
    // Internal Wires
    wire [4:0] counter_address;
    wire [31:0] imm_gen_inst;
    wire [4:0] rs1, rs2, rd;
    wire regWrite, memToReg, memWrite, operandA, operandB;
    wire branch, jalrEN, jalEN;
    wire [5:0] aluOP;
    wire [31:0] write_data, read_data1, read_data2;
    wire [31:0] aluOut, PC, instMemOUT, dataMemOUT, load_write;

    // Counter Module
    Counter u_Counter (
        .rst(rst),
        .clk(clk),
        .out(PC)
    );

    assign counter_address = PC[6:2];

    reg [31:0] MEM [0:31];

    initial begin
        $readmemh("file.mem",MEM);
    end 

    // Instruction Memory (RAM1)
    RAM u_RAM1 (
        .clk(clk),
        .readWrite(RW), // Read-only 
        .address(counter_address),
        .dataIN(dataIN),   
        .dataOUT(instMemOUT)
    );

    // Control Decoder
    ControlDecoder u_ControlDecode (
        .instruction(instMemOUT),
        .imm_gen_inst(imm_gen_inst),
        .rs1(rs1),
        .rs2(rs2),
        .rd(rd),
        .regWrite(regWrite),
        .memToReg(memToReg),
        .memWrite(memWrite),
        .operandA(operandA),
        .operandB(operandB),
        .aluOP(aluOP)
    );

    // Register File
    register o_register (
        .clk(clk),
        .reset(rst),
        .regWrite(regWrite),
        .write_data(write_data),
        .rd_data(rd),
        .rs1_data(rs1),
        .rs2_data(rs2),
        .read_data1(read_data1),
        .read_data2(read_data2)
    );
    wire [31:0] OpA;
    wire [31:0] OpB;
    assign OpA = operandA ? imm_gen_inst : read_data1;
    assign OpB = operandB ? PC  : read_data2;

    // ALU
    alu u_alu (
        .a(OpA),
        .b(OpB),
        .opcode(aluOP),
        .c(aluOut)
    );

    // Data Memory (RAM2)
    RAM u_RAM2 (
        .clk(clk),
        .readWrite(memWrite), 
        .address(aluOut[6:2]), 
        .dataIN(read_data2),   
        .dataOUT(dataMemOUT)
    );

    // Data Memory Interface (DMI)
    DMI u_DMI (
        .load(dataMemOUT),
        .aluOP(aluOP),
        .load_data(load_write)
    );

    // Write Back
    assign write_data = memToReg ? load_write : aluOut;

endmodule

single_cycle_dev/verilog_zaid/main/tb/main_tb.v
module MAIN_tb();
    reg clk;
    reg [31:0]dataIN;
    reg rst;
    reg en;
    reg RW;


always begin
    #5 clk = ~clk;
end

MAIN u_MAIN(
    .clk(clk),
    .dataIN(dataIN),
    .rst(rst),
    .en(en),
    .RW(RW)
);


initial begin
    clk = 1;
    rst = 0;
    RW = 0;
    en = 1;
    #5 rst = 1;
    #10 rst = 0;

    dataIN = 32'h00400093;  #10;// ADDI x1, x0, 4
    dataIN = 32'h00500113;  #10;// ADDI x2, x0, 5
    dataIN = 32'h40110233;  #10 RW = 1; // SUB x4, x2, x1

    #100 $finish;
end


initial begin
    $dumpfile("temp/main.vcd");
    $dumpvars(0,MAIN_tb); 
end


endmodule

single_cycle_dev/verilog_zaid/main/temp/main.vcd
$date
	Mon Dec  2 17:09:54 2024
$end
$version
	Icarus Verilog
$end
$timescale
	1s
$end
$scope module MAIN_tb $end
$var reg 1 ! RW $end
$var reg 1 " clk $end
$var reg 32 # dataIN [31:0] $end
$var reg 1 $ en $end
$var reg 1 % rst $end
$scope module u_MAIN $end
$var wire 1 ! RW $end
$var wire 1 " clk $end
$var wire 32 & dataIN [31:0] $end
$var wire 1 $ en $end
$var wire 1 % rst $end
$var wire 32 ' write_data [31:0] $end
$var wire 5 ( rs2 [4:0] $end
$var wire 5 ) rs1 [4:0] $end
$var wire 1 * regWrite $end
$var wire 32 + read_data2 [31:0] $end
$var wire 32 , read_data1 [31:0] $end
$var wire 5 - rd [4:0] $end
$var wire 1 . operandB $end
$var wire 1 / operandA $end
$var wire 1 0 memWrite $end
$var wire 1 1 memToReg $end
$var wire 32 2 load_write [31:0] $end
$var wire 32 3 instMemOUT [31:0] $end
$var wire 32 4 imm_gen_inst [31:0] $end
$var wire 32 5 dataMemOUT [31:0] $end
$var wire 5 6 counter_address [4:0] $end
$var wire 32 7 aluOut [31:0] $end
$var wire 6 8 aluOP [5:0] $end
$var wire 32 9 PC [31:0] $end
$var wire 32 : OpB [31:0] $end
$var wire 32 ; OpA [31:0] $end
$scope module o_register $end
$var wire 1 " clk $end
$var wire 1 % reset $end
$var wire 32 < write_data [31:0] $end
$var wire 5 = rs2_data [4:0] $end
$var wire 5 > rs1_data [4:0] $end
$var wire 1 * regWrite $end
$var wire 5 ? rd_data [4:0] $end
$var reg 32 @ read_data1 [31:0] $end
$var reg 32 A read_data2 [31:0] $end
$var integer 32 B i [31:0] $end
$upscope $end
$scope module u_ControlDecode $end
$var wire 5 C rs2 [4:0] $end
$var wire 5 D rs1 [4:0] $end
$var wire 5 E rd [4:0] $end
$var wire 7 F opcode [6:0] $end
$var wire 32 G instruction [31:0] $end
$var wire 7 H func7 [6:0] $end
$var wire 3 I func3 [2:0] $end
$var reg 6 J aluOP [5:0] $end
$var reg 1 K branch $end
$var reg 32 L imm_gen_inst [31:0] $end
$var reg 1 M jalEN $end
$var reg 1 N jalrEN $end
$var reg 1 1 memToReg $end
$var reg 1 0 memWrite $end
$var reg 1 / operandA $end
$var reg 1 . operandB $end
$var reg 1 * regWrite $end
$upscope $end
$scope module u_Counter $end
$var wire 1 " clk $end
$var wire 32 O o [31:0] $end
$var wire 1 % rst $end
$var reg 32 P out [31:0] $end
$upscope $end
$scope module u_DMI $end
$var wire 32 Q LW [31:0] $end
$var wire 6 R aluOP [5:0] $end
$var wire 32 S load [31:0] $end
$var wire 16 T LHU [15:0] $end
$var wire 16 U LH [15:0] $end
$var wire 8 V LBU [7:0] $end
$var wire 8 W LB [7:0] $end
$var reg 32 X load_data [31:0] $end
$upscope $end
$scope module u_RAM1 $end
$var wire 5 Y address [4:0] $end
$var wire 1 " clk $end
$var wire 32 Z dataIN [31:0] $end
$var wire 1 ! readWrite $end
$var reg 32 [ dataOUT [31:0] $end
$upscope $end
$scope module u_RAM2 $end
$var wire 5 \ address [4:0] $end
$var wire 1 " clk $end
$var wire 32 ] dataIN [31:0] $end
$var wire 1 0 readWrite $end
$var reg 32 ^ dataOUT [31:0] $end
$upscope $end
$scope module u_alu $end
$var wire 32 _ a [31:0] $end
$var wire 32 ` b [31:0] $end
$var wire 6 a opcode [5:0] $end
$var reg 32 b c [31:0] $end
$upscope $end
$upscope $end
$upscope $end
$enddefinitions $end
#0
$dumpvars
bx b
bx a
bx `
bx _
bx ^
bx ]
bx \
bx [
bx Z
bx Y
bx X
bx W
bx V
bx U
bx T
bx S
bx R
bx Q
bx P
b100 O
xN
xM
bx L
xK
bx J
bx I
bx H
bx G
bx F
bx E
bx D
bx C
bx B
bx A
bx @
bx ?
bx >
bx =
bx <
bx ;
bx :
bx 9
bx 8
bx 7
bx 6
bx 5
bx 4
bx 3
bx 2
x1
x0
x/
x.
bx -
bx ,
bx +
x*
bx )
bx (
bx '
bx &
0%
1$
bx #
1"
0!
$end
#5
b0 6
b0 Y
b0 9
b0 P
1%
0"
#10
b100000 B
1"
#15
0"
b10000000000000010010011 #
b10000000000000010010011 &
b10000000000000010010011 Z
0%
#20
b1 6
b1 Y
b100 9
b100 P
1"
#25
0"
b10100000000000100010011 #
b10100000000000100010011 &
b10100000000000100010011 Z
#30
b10 6
b10 Y
b1000 9
b1000 P
1"
#35
0"
b1000000000100010000001000110011 #
b1000000000100010000001000110011 &
b1000000000100010000001000110011 Z
#40
b11 6
b11 Y
b1100 9
b1100 P
1"
#45
0"
1!
#50
b100 '
b100 <
b1 \
b100 7
b100 b
b0 :
b0 `
b100 ;
b100 _
b0 +
b0 A
b0 ]
b0 ,
b0 @
0M
0N
b101 8
b101 J
b101 R
b101 a
0K
0.
1/
00
01
1*
b100 (
b100 =
b100 C
b0 )
b0 >
b0 D
b1 -
b1 ?
b1 E
b0 H
b0 I
b10011 F
b100 4
b100 L
b100 6
b100 Y
b10000000000000010010011 3
b10000000000000010010011 G
b10000000000000010010011 [
b10000 9
b10000 P
1"
#55
0"
#60
b101 '
b101 <
b101 7
b101 b
b101 ;
b101 _
b101 (
b101 =
b101 C
b10 -
b10 ?
b10 E
b101 4
b101 L
b101 6
b101 Y
b10100000000000100010011 3
b10100000000000100010011 G
b10100000000000100010011 [
b10100 9
b10100 P
1"
#65
0"
#70
b1 '
b1 <
b0 \
b1 7
b1 b
b100 :
b100 `
b10011 8
b10011 J
b10011 R
b10011 a
0/
1*
b101 ;
b101 _
b100 +
b100 A
b100 ]
b101 ,
b101 @
b1 (
b1 =
b1 C
b10 )
b10 >
b10 D
b100 -
b100 ?
b100 E
b100000 H
b110011 F
b0 4
b0 L
b110 6
b110 Y
b1000000000100010000001000110011 3
b1000000000100010000001000110011 G
b1000000000100010000001000110011 [
b11000 9
b11000 P
1"
#75
0"
#80
b0 '
b0 <
bx :
bx `
bx ;
bx _
b0 7
b0 b
bx +
bx A
bx ]
bx ,
bx @
b0 8
b0 J
b0 R
b0 a
0*
bx (
bx =
bx C
bx )
bx >
bx D
bx -
bx ?
bx E
bx H
bx I
bx F
b111 6
b111 Y
bx 3
bx G
bx [
b11100 9
b11100 P
1"
#85
0"
#90
b1000 6
b1000 Y
b100000 9
b100000 P
1"
#95
0"
#100
b1001 6
b1001 Y
b100100 9
b100100 P
1"
#105
0"
#110
b1010 6
b1010 Y
b101000 9
b101000 P
1"
#115
0"
#120
b1011 6
b1011 Y
b101100 9
b101100 P
1"
#125
0"
#130
b1100 6
b1100 Y
b110000 9
b110000 P
1"
#135
0"
#140
b1101 6
b1101 Y
b110100 9
b110100 P
1"
