single_cycle_dev/verilog_zaid/main/src/writeBack.v
module WriteBack (
    input wire clk,
    input wire [31:0] load_write,
    input wire [31:0] PC_in,
    input wire [31:0] aluOut,
    input wire memToReg,
    input wire jalEN,
    input wire jalrEN,
    output reg [31:0] write_data,
    output reg [31:0] PC_out,
    output reg jump
);
    always @(posedge clk) begin
        jump = 0;
        if ( jalEN || jalrEN ) begin
            write_data <= PC_in + 4;
            PC_out <= aluOut; 
            jump <= 1;
        end
    end

    always @(*) begin
        if (memToReg) begin
            write_data = load_write;
        end
        else begin
            write_data = aluOut;
        end
    end
endmodule

single_cycle_dev/verilog_zaid/main/src/data_mem_intf.v
module DMI(
    input wire [31:0]load,
    input wire [5:0]aluOP,
    input wire [31:0] rs2,
    output reg [31:0]load_data,
    output reg [31:0]store_data
);
localparam loadByte = 6'd0;
localparam loadHalf = 6'd1;
localparam loadByteUnsigned = 6'd3;
localparam loadHalfUnsigned = 6'd4;
localparam loadWord = 6'd2;
localparam storeWord = 6'd17;
localparam storeHalf = 6'd16;
localparam storeByte = 6'd15;

wire [7:0]LB;
wire [15:0]LH;
wire [7:0]LBU;
wire [15:0]LHU;
wire [31:0]LW;

wire [31:0] SW;
wire [15:0] SH;
wire [7:0] SB;

assign LB = load[7:0];
assign LH = load[15:0];
assign LBU = load[7:0];
assign LHU = load[15:0];
assign LW = load[31:0];

assign SW = rs2;
assign SH = rs2[15:0];
assign SB = rs2[7:0];

always @(*) begin
    case(aluOP)
    loadByte: begin
        load_data = $signed({{24{LB[7]}},LB}); // load bite
    end
    loadHalf: begin
        load_data = $signed({{16{LH[15]}},LH}); // load half bite
    end
    loadByteUnsigned: begin
        load_data = $unsigned({24'b0,LBU}); //load bite unsigned
    end
    loadHalfUnsigned: begin
        load_data = $unsigned({16'b0, LHU}); //load halfword unsigned 
    end
    loadWord: begin
        load_data = LW; //load word remains same 
    end
    storeWord: begin
        store_data = SW;     // store word 
    end
    storeHalf: begin
        store_data = $unsigned({16'b0, SH});    // store half word 
    end
    storeByte: begin
        store_data = $unsigned({24'b0, SB});    // store byte
    end
    default: begin
    load_data = 32'b0;
    store_data = 32'b0;
    end
    endcase
end

endmodule

five_stage_pipeline_dev/verilog_zaid/main/src/RAM.v
module RAM (
    input wire clk,
    input wire [31:0] MemWrite,
    input wire [31:0] rs1,
    input wire [31:0] rd,
    input wire [31:0] Immediate,
    input wire memToReg,
    input wire memWrite,   
    output reg [31:0] MemRead
);
    reg [31:0] RAM [0:31]; 

    reg [31:0] loc;
    reg [4:0] address;

    integer i;

    initial begin
        for (i = 0; i < 32; i = i + 1) begin
        RAM[i] = 32'd0;
    end
    end

    always @(*) begin
    if (memToReg) begin             
            loc = rs1 + Immediate;
            address = loc [4:0];
    end
    else if (memWrite) begin
            loc = rd + Immediate;
            address = loc [4:0];
    end
    end

    always @(posedge clk) begin
        if (memToReg) begin              //readWrite true -> Read and false -> Write
            MemRead <= RAM[address];

        end 
        else if (memWrite) begin
            RAM[address] <= MemWrite;
        end
    end
    always @(*) begin
    if (memToReg) begin
        MemRead = RAM[address];
    end
end


endmodule

single_cycle_dev/verilog_zaid/main/src/alu.v
module alu(
  input wire [31:0]a,
  input wire [31:0]b,
  input wire [5:0]opcode,
  output reg [31:0]c
);

  reg temp [31:0];

  always @(*) begin
        case(opcode) 
        6'd5: c = a + b;
        6'd6: c = a << b;
        6'd7: c = ($signed(a) < $signed(b)) ? 32'b1 : 32'b0;
        6'd8: c = ($unsigned(a) < $unsigned(b) ) ? 32'b1 : 32'b0;
        6'd9: c = a ^ b;
        6'd10: c = a >> b;
        6'd11: c = a >>> b;
        6'd12: c = a | b;
        6'd13: c = a & b;
        6'd18: c = a + b;
        6'd19: c = a - b;
        6'd20: c = a << b;
        6'd21: c = ($unsigned(a) < $unsigned(b)) ? 32'b1 : 32'b0;
        6'd22: c = ($unsigned(a) < $unsigned(b)) ? 32'b1 : 32'b0;
        6'd23: c = a ^ b; 
        6'd24: c = a >> b; 
        6'd25: c = a >>> b; 
        6'd26: c = a | b;
        6'd27: c = a & b;
        6'd28: c = b;                               //lui
        6'd14 , 6'd35 , 6'd36: c = a + b;          //auipc , jalr , jal                
        default: c = 32'b0;
        endcase
  end
endmodule

single_cycle_dev/verilog_zaid/main/src/registerfile.v
module register (
    input wire clk,
    input wire reset,
    input wire regWrite, 
    input [31:0] write_data,
    input [4:0] rd_data,
    input [4:0] rs1_data,
    input [4:0] rs2_data,
    output reg [31:0] read_data1,
    output reg [31:0] read_data2
);
    reg [31:0] registerf [0:31];
    integer i;

    // Synchronous
    always @(posedge clk) begin
        if (reset || ~regWrite) begin
            for (i = 0; i < 32; i = i + 1) 
                registerf[i] <= 32'b0; 
        end else if (regWrite && rd_data != 0) begin
            registerf[rd_data] <= write_data; 
        end
    end

    // ASynchronous
    always @(*) begin
        read_data1 = (rs1_data == 0) ? 32'b0 : registerf[rs1_data];
        read_data2 = (rs2_data == 0) ? 32'b0 : registerf[rs2_data];
    end

endmodule

single_cycle_dev/verilog_zaid/main/src/control_decode.v
module ControlDecoder(
    input wire [31:0] instruction,
    output reg [31:0] imm_gen_inst,
    output wire [4:0] rs1,
    output wire [4:0] rs2,
    output wire [4:0] rd,
    output reg regWrite,
    output reg memToReg,
    output reg memWrite,
    output reg operandA,
    output reg operandB,
    output reg branch,
    output reg [5:0] aluOP,
    output reg jalrEN,
    output reg jalEN
);

localparam load_Itype = 7'b0000011;
localparam alu_Itype = 7'b0010011;
localparam jalr_Itype = 7'b1100111;
localparam alu_rtype = 7'b0110011; 
localparam store = 7'b0100011; //0100011

// instr decode
wire [6:0] opcode = instruction[6:0];
wire [2:0] func3 = instruction[14:12];
wire [6:0] func7 = instruction[31:25];
reg [11:0] split_inst;
reg [20:0] split_inst2;

assign rd = instruction[11:7];
assign rs1 = instruction[19:15];
assign rs2 = instruction[24:20];

// Immediate generation logic
always @(*) begin
    case (opcode)
        load_Itype, alu_Itype, jalr_Itype: begin
            imm_gen_inst = {{20{instruction[31]}}, instruction[31:20]};  //laod , alu_i-type and jalr_i-type
        end
        7'd35: begin   
            split_inst [4:0] = instruction [11:7];
            split_inst [11:5] = instruction [31:25];                                                   //store instruction 
            imm_gen_inst = {{20{split_inst[11]}}, split_inst};
        end
        7'd23 , 7'd55: begin                                //auipc and lui U-type
            imm_gen_inst = {instruction[31:12], 12'b0};
        end
        7'd111: begin                               //jal-UJ
            split_inst2 [0] = 1'b0;
            split_inst2 [20] = instruction [31];
            split_inst2 [11] = instruction [20];
            split_inst2 [10:1] = instruction [30:21];
            split_inst2 [19:12] = instruction [19:12];
            imm_gen_inst = {{11{split_inst2[20]}}, split_inst2};
        end
        default: begin
            imm_gen_inst = 32'b0;
        end
    endcase
end

// Control decode logic
always @(*) begin
    regWrite = 0;
    memToReg = 0;
    memWrite = 0;
    operandA = 0;
    operandB = 0;
    branch = 0;
    aluOP = 6'd0;
    jalrEN = 0;
    jalEN = 0;

    case (opcode)
        alu_rtype: begin
            case (func3)
                3'd0: aluOP = func7[5] ? 6'd19 : 6'd18;  // SUB or ADD
                3'd1: aluOP = 6'd20;  // SLL
                3'd2: aluOP = 6'd21;  // SLT
                3'd3: aluOP = 6'd22;  // SLTU
                3'd4: aluOP = 6'd23;  // XOR
                3'd5: aluOP = func7[5] ? 6'd25 : 6'd24;  // SRA or SRL
                3'd6: aluOP = 6'd26;  // OR
                3'd7: aluOP = 6'd27;  // AND
            endcase
            regWrite = 1;
        end
        alu_Itype: begin
            case (func3)
                3'd0: aluOP = 6'd5;   // ADDI
                3'd1: aluOP = 6'd6;   // SLLI
                3'd2: aluOP = 6'd7;   // SLTI
                3'd3: aluOP = 6'd8;   // SLTIU
                3'd4: aluOP = 6'd9;   // XORI
                3'd5: aluOP = func7[5] ? 6'd11 : 6'd10;  // SRAI or SRLI
                3'd6: aluOP = 6'd12;  // ORI
                3'd7: aluOP = 6'd13;  // ANDI
            endcase
            regWrite = 1;
            operandA = 1;
        end
        load_Itype: begin
            case (func3)
                3'd0: aluOP = 6'd0;  // LB
                3'd1: aluOP = 6'd1;  // LH
                3'd2: aluOP = 6'd2;  // LW
                3'd3: aluOP = 6'd3;  // LD
                3'd4: aluOP = 6'd4;  // LBU
            endcase
            regWrite = 1;
            memToReg = 1;
            operandA = 1;
        end
        jalr_Itype: begin
            aluOP = 6'd35;  // JALR operation
            regWrite = 1;
            operandA = 1;
            jalrEN = 1;
        end
        7'd35: begin
            case(func3)
                3'd0: aluOP = 6'd15;  // SB
                3'd1: aluOP = 6'd16;  // SH
                3'd2: aluOP = 6'd17;  // SW
            endcase
                memWrite = 1;
                operandA = 1;
        end
        7'd23: begin        //AUIPC
            aluOP = 6'd14;
            regWrite = 1;
            operandA = 1;
            operandB = 1;
        end
        7'd55: begin        //LUI
            aluOP = 6'd28;
            regWrite = 1;
            operandA = 1;
        end 
        7'd111: begin       //jal
            aluOP = 6'd36;
            regWrite = 1;
            operandA = 1;
            operandB = 1;
            jalEN = 1;
        end
    endcase
end

endmodule

single_cycle_dev/verilog_zaid/main/src/fetch.v
module fetch(
    input wire clk,
    input wire rst,
    input wire en,
    input wire jump,
    input wire [31:0] JPC,
    output reg [31:0] counterOUT,  
    output reg [4:0] mem_address,  
    output reg [31:0] instruction       
);

    reg [31:0] FPC;  
    reg [31:0] INST_MEM [0:31];  
    
    initial begin
        $readmemh("file.mem", INST_MEM);
    end

    always @(*) begin
    if (~jump) begin
        FPC = counterOUT;
    end else begin
        FPC = JPC;
    end
    end

    always @(posedge clk or posedge rst) begin
        if (rst) begin
            FPC <= 32'd0; // Reset PC to zero
        end else if (en) begin
            FPC <= FPC + 32'd4; // Increment PC by 4 when enabled
        end
    end

    always @(*) begin
        counterOUT = FPC;
        mem_address = FPC[6:2];  // Word-aligned memory address
        instruction = INST_MEM[mem_address];
    end

endmodule

single_cycle_dev/verilog_zaid/main/src/main.v
module MAIN (
    input wire clk,
    input [31:0] dataIN,
    input wire rst,
    input wire en,
    input wire RW
);
    // Internal Wires
    wire [4:0] counter_address;
    wire [31:0] imm_gen_inst;
    wire [4:0] rs1, rs2, rd;
    wire regWrite, memToReg, memWrite, readWrite , operandA, operandB;
    wire branch, jalrEN, jalEN , jump;
    wire [5:0] aluOP;
    wire [31:0] write_data, read_data1, read_data2;
    wire [31:0] aluOut, PC, JPC , instMemOUT, dataMemLoad, load_write , store_data;

    // Fetch Stage
    fetch u_fetch(
        .clk(clk),
        .rst(rst),
        .en(en),
        .JPC(JPC),
        .counterOUT(PC),
        .mem_address(counter_address),
        .instruction(instMemOUT),
        .jump(jump)
    );

    // Control Decoder
    ControlDecoder u_ControlDecode (
        .instruction(instMemOUT),
        .imm_gen_inst(imm_gen_inst),
        .rs1(rs1),
        .rs2(rs2),
        .rd(rd),
        .regWrite(regWrite),
        .memToReg(memToReg),
        .memWrite(memWrite),
        .operandA(operandA),
        .operandB(operandB),
        .aluOP(aluOP),
        .jalrEN(jalrEN),
        .jalEN(jalEN)
    );

    // Register File
    register o_register (
        .clk(clk),
        .reset(rst),
        .regWrite(regWrite),
        .write_data(write_data),
        .rd_data(rd),
        .rs1_data(rs1),
        .rs2_data(rs2),
        .read_data1(read_data1),
        .read_data2(read_data2)
    );
    wire [31:0] OpA;
    wire [31:0] OpB;
    assign OpA = operandA ? imm_gen_inst : read_data1;
    assign OpB = operandB ? PC  : read_data2;
    assign readWrite = (memToReg) ? 1 : (memWrite) ? 0 : -1;
    // ALU
    alu u_alu (
        .a(OpA),
        .b(OpB),
        .opcode(aluOP),
        .c(aluOut)
    );

    // Data Memory (RAM2)
    RAM u_RAM2 (
        .clk(clk),
        .rs1(read_data1),
        .rd(write_data),
        .Immediate(imm_gen_inst),
        .memToReg(memToReg),
        .memWrite(memWrite),
        .MemWrite(store_data),  
        .MemRead(dataMemLoad)
    );

    // Data Memory Interface (DMI)
    DMI u_DMI (
        .load(dataMemLoad),
        .rs2(read_data2),
        .store_data(store_data),
        .aluOP(aluOP),
        .load_data(load_write)
    );

    WriteBack u_WriteBack (
    .clk(clk),
    .load_write(load_write),
    .PC_in(PC),
    .aluOut(aluOut),
    .memToReg(memToReg),
    .jalEN(jalEN),
    .jalrEN(jalrEN),
    .write_data(write_data),
    .PC_out(JPC),
    .jump(jump)
);

endmodule

single_cycle_dev/verilog_zaid/main/tb/main_tb.v
module MAIN_tb();
    reg clk;
    reg [31:0]dataIN;
    reg rst;
    reg en;
    reg RW;


always begin
    #5 clk = ~clk;
end

MAIN u_MAIN(
    .clk(clk),
    .dataIN(dataIN),
    .rst(rst),
    .en(en),
    .RW(RW)
);


initial begin
    clk = 1;
    rst = 1;
    #5 rst = 0;
    en = 1;
    #10 rst = 1;
    #5 rst = 0;
    #450 en = 0;
    #500 $finish;
end


initial begin
    $dumpfile("temp/main.vcd");
    $dumpvars(0,MAIN_tb); 
end


endmodule

single_cycle_dev/verilog_zaid/main/temp/main.vcd
$date
	Sun Dec  8 18:49:57 2024
$end
$version
	Icarus Verilog
$end
$timescale
	1s
$end
$scope module MAIN_tb $end
$var reg 1 ! RW $end
$var reg 1 " clk $end
$var reg 32 # dataIN [31:0] $end
$var reg 1 $ en $end
$var reg 1 % rst $end
$scope module u_MAIN $end
$var wire 1 ! RW $end
$var wire 1 " clk $end
$var wire 32 & dataIN [31:0] $end
$var wire 1 $ en $end
$var wire 1 % rst $end
$var wire 32 ' write_data [31:0] $end
$var wire 32 ( store_data [31:0] $end
$var wire 5 ) rs2 [4:0] $end
$var wire 5 * rs1 [4:0] $end
$var wire 1 + regWrite $end
$var wire 32 , read_data2 [31:0] $end
$var wire 32 - read_data1 [31:0] $end
$var wire 1 . readWrite $end
$var wire 5 / rd [4:0] $end
$var wire 1 0 operandB $end
$var wire 1 1 operandA $end
$var wire 1 2 memWrite $end
$var wire 1 3 memToReg $end
$var wire 32 4 load_write [31:0] $end
$var wire 1 5 jump $end
$var wire 1 6 jalrEN $end
$var wire 1 7 jalEN $end
$var wire 32 8 instMemOUT [31:0] $end
$var wire 32 9 imm_gen_inst [31:0] $end
$var wire 32 : dataMemLoad [31:0] $end
$var wire 5 ; counter_address [4:0] $end
$var wire 32 < aluOut [31:0] $end
$var wire 6 = aluOP [5:0] $end
$var wire 32 > PC [31:0] $end
$var wire 32 ? OpB [31:0] $end
$var wire 32 @ OpA [31:0] $end
$var wire 32 A JPC [31:0] $end
$scope module o_register $end
$var wire 1 " clk $end
$var wire 1 % reset $end
$var wire 32 B write_data [31:0] $end
$var wire 5 C rs2_data [4:0] $end
$var wire 5 D rs1_data [4:0] $end
$var wire 1 + regWrite $end
$var wire 5 E rd_data [4:0] $end
$var reg 32 F read_data1 [31:0] $end
$var reg 32 G read_data2 [31:0] $end
$var integer 32 H i [31:0] $end
$upscope $end
$scope module u_ControlDecode $end
$var wire 5 I rs2 [4:0] $end
$var wire 5 J rs1 [4:0] $end
$var wire 5 K rd [4:0] $end
$var wire 7 L opcode [6:0] $end
$var wire 32 M instruction [31:0] $end
$var wire 7 N func7 [6:0] $end
$var wire 3 O func3 [2:0] $end
$var reg 6 P aluOP [5:0] $end
$var reg 1 Q branch $end
$var reg 32 R imm_gen_inst [31:0] $end
$var reg 1 7 jalEN $end
$var reg 1 6 jalrEN $end
$var reg 1 3 memToReg $end
$var reg 1 2 memWrite $end
$var reg 1 1 operandA $end
$var reg 1 0 operandB $end
$var reg 1 + regWrite $end
$var reg 12 S split_inst [11:0] $end
$var reg 21 T split_inst2 [20:0] $end
$upscope $end
$scope module u_DMI $end
$var wire 32 U LW [31:0] $end
$var wire 32 V SW [31:0] $end
$var wire 6 W aluOP [5:0] $end
$var wire 32 X rs2 [31:0] $end
$var wire 32 Y load [31:0] $end
$var wire 16 Z SH [15:0] $end
$var wire 8 [ SB [7:0] $end
$var wire 16 \ LHU [15:0] $end
$var wire 16 ] LH [15:0] $end
$var wire 8 ^ LBU [7:0] $end
$var wire 8 _ LB [7:0] $end
$var reg 32 ` load_data [31:0] $end
$var reg 32 a store_data [31:0] $end
$upscope $end
$scope module u_RAM2 $end
$var wire 32 b Immediate [31:0] $end
$var wire 32 c MemWrite [31:0] $end
$var wire 1 " clk $end
$var wire 1 3 memToReg $end
$var wire 1 2 memWrite $end
$var wire 32 d rs1 [31:0] $end
$var wire 32 e rd [31:0] $end
$var reg 32 f MemRead [31:0] $end
$var reg 5 g address [4:0] $end
$var reg 32 h loc [31:0] $end
$var integer 32 i i [31:0] $end
$upscope $end
$scope module u_WriteBack $end
$var wire 1 " clk $end
$var wire 1 7 jalEN $end
$var wire 1 6 jalrEN $end
$var wire 32 j load_write [31:0] $end
$var wire 1 3 memToReg $end
$var wire 32 k aluOut [31:0] $end
$var wire 32 l PC_in [31:0] $end
$var reg 32 m PC_out [31:0] $end
$var reg 1 5 jump $end
$var reg 32 n write_data [31:0] $end
$upscope $end
$scope module u_alu $end
$var wire 32 o a [31:0] $end
$var wire 32 p b [31:0] $end
$var wire 6 q opcode [5:0] $end
$var reg 32 r c [31:0] $end
$upscope $end
$scope module u_fetch $end
$var wire 32 s JPC [31:0] $end
$var wire 1 " clk $end
$var wire 1 $ en $end
$var wire 1 5 jump $end
$var wire 1 % rst $end
$var reg 32 t FPC [31:0] $end
$var reg 32 u counterOUT [31:0] $end
$var reg 32 v instruction [31:0] $end
$var reg 5 w mem_address [4:0] $end
$upscope $end
$upscope $end
$upscope $end
$enddefinitions $end
#0
$dumpvars
b0 w
b10100000000000110010011 v
b0 u
b0 t
bx s
b101 r
b101 q
b0 p
b101 o
b101 n
bx m
b0 l
b101 k
b0 j
b100000 i
bx h
bx g
bx f
b101 e
b0 d
b0 c
b101 b
b0 a
b0 `
bx _
bx ^
bx ]
bx \
b0 [
b0 Z
bx Y
b0 X
b101 W
b0 V
bx U
bx T
bx S
b101 R
0Q
b101 P
b0 O
b0 N
b10100000000000110010011 M
b10011 L
b11 K
b0 J
b101 I
b100000 H
b0 G
b0 F
b11 E
b0 D
b101 C
b101 B
bx A
b101 @
b0 ?
b0 >
b101 =
b101 <
b0 ;
bx :
b101 9
b10100000000000110010011 8
07
06
05
b0 4
03
02
11
00
b11 /
1.
b0 -
b0 ,
1+
b0 *
b101 )
b0 (
b101 '
bx &
1%
x$
bx #
1"
x!
$end
#5
1$
0%
0"
#10
b10 '
b10 B
b10 e
b10 n
b10 <
b10 k
b10 r
b10 @
b10 o
b10 )
b10 C
b10 I
b1 /
b1 E
b1 K
b10 9
b10 R
b10 b
b1000000000000010010011 8
b1000000000000010010011 M
b1000000000000010010011 v
b1 ;
b1 w
b100 >
b100 l
b100 u
b100 t
1"
#15
b101 '
b101 B
b101 e
b101 n
b101 <
b101 k
b101 r
b101 @
b101 o
b101 )
b101 C
b101 I
b11 /
b11 E
b11 K
b101 9
b101 R
b101 b
b10100000000000110010011 8
b10100000000000110010011 M
b10100000000000110010011 v
b0 ;
b0 w
b0 >
b0 l
b0 u
b0 t
0"
1%
#20
b10 '
b10 B
b10 e
b10 n
b10 <
b10 k
b10 r
b10 @
b10 o
b10 )
b10 C
b10 I
b1 /
b1 E
b1 K
b10 9
b10 R
b10 b
b1000000000000010010011 8
b1000000000000010010011 M
b1000000000000010010011 v
b1 ;
b1 w
b100 >
b100 l
b100 u
b100 t
1"
0%
#25
0"
#30
0.
b101 (
b101 a
b101 c
b0 '
b0 B
b0 e
b0 n
b101 Z
b101 [
b101 ?
b101 p
b11101 g
b11111111111111111111111111111101 h
b0 <
b0 k
b0 r
b101 V
b101 ,
b101 G
b101 X
b10 -
b10 F
b10 d
12
b1111 =
b1111 P
b1111 W
b1111 q
11
0+
b111111111101 S
b11111111111111111111111111111101 @
b11111111111111111111111111111101 o
b11 )
b11 C
b11 I
b1 *
b1 D
b1 J
b11101 /
b11101 E
b11101 K
b1111111 N
b100011 L
b11111111111111111111111111111101 9
b11111111111111111111111111111101 R
b11111111111111111111111111111101 b
b11111110001100001000111010100011 8
b11111110001100001000111010100011 M
b11111110001100001000111010100011 v
b10 ;
b10 w
b1000 >
b1000 l
b1000 u
b1000 t
1"
#35
0"
#40
1.
b101 \
b101 ^
b101 ]
b101 _
b101 '
b101 B
b101 e
b101 n
b101 4
b101 `
b101 j
b101 U
b101 :
b101 Y
b101 f
13
1+
b0 =
b0 P
b0 W
b0 q
11
02
b11111111111111111111111111111101 @
b11111111111111111111111111111101 o
b0 (
b0 a
b0 c
b0 Z
b0 [
b0 ?
b0 p
b11101 g
b11111111111111111111111111111101 h
b11101 )
b11101 C
b11101 I
b100 /
b100 E
b100 K
b11 L
b11111111111111111111111111111101 9
b11111111111111111111111111111101 R
b11111111111111111111111111111101 b
b111111100100 S
b0 V
b0 ,
b0 G
b0 X
b0 -
b0 F
b0 d
b11111111110100001000001000000011 8
b11111111110100001000001000000011 M
b11111111110100001000001000000011 v
b11 ;
b11 w
b1100 >
b1100 l
b1100 u
b1100 t
b100000 H
1"
#45
0"
#50
b10000 ?
b10000 p
b0 4
b0 `
b0 j
b0 '
b0 B
b0 e
b0 n
b0 <
b0 k
b0 r
17
10
b100100 =
b100100 P
b100100 W
b100100 q
11
03
1+
b111111111111111110000 T
b10001 g
b11111111111111111111111111110001 h
b11111111111111111111111111110000 @
b11111111111111111111111111110000 o
b10001 )
b10001 C
b10001 I
b11111 *
b11111 D
b11111 J
b10 /
b10 E
b10 K
b111 O
b1101111 L
b11111111111111111111111111110000 9
b11111111111111111111111111110000 R
b11111111111111111111111111110000 b
b11111111000111111111000101101111 8
b11111111000111111111000101101111 M
b11111111000111111111000101101111 v
b100 ;
b100 w
b10000 >
b10000 l
b10000 u
b10000 t
1"
#55
0"
#60
b0 Z
b0 [
b0 4
b0 `
b0 j
b0 V
b0 ,
b0 G
b0 X
b0 -
b0 F
b0 d
07
b101 =
b101 P
b101 W
b101 q
00
11
1+
b101 @
b101 o
b101 <
b101 k
b101 r
b101 )
b101 C
b101 I
b0 *
b0 D
b0 J
b11 /
b11 E
b11 K
b0 N
b0 O
b10011 L
b101 9
b101 R
b101 b
bx0 T
b0 ?
b0 p
b10100000000000110010011 8
b10100000000000110010011 M
b10100000000000110010011 v
b0 ;
b0 w
b0 >
b0 l
b0 u
15
b0 A
b0 m
b0 s
b101 '
b101 B
b101 e
b101 n
b0 t
1"
#65
0"
#70
b10 '
b10 B
b10 e
b10 n
b10 <
b10 k
b10 r
b10 @
b10 o
b10 )
b10 C
b10 I
b1 /
b1 E
b1 K
b10 9
b10 R
b10 b
b1000000000000010010011 8
b1000000000000010010011 M
b1000000000000010010011 v
b1 ;
b1 w
b100 >
b100 l
b100 u
b100 t
05
1"
#75
0"
#80
0.
b101 (
b101 a
b101 c
b0 '
b0 B
b0 e
b0 n
b101 Z
b101 [
b101 ?
b101 p
b11101 g
b11111111111111111111111111111101 h
b0 <
b0 k
b0 r
b101 V
b101 ,
b101 G
b101 X
b10 -
b10 F
b10 d
12
b1111 =
b1111 P
b1111 W
b1111 q
11
0+
b111111111101 S
b11111111111111111111111111111101 @
b11111111111111111111111111111101 o
b11 )
b11 C
b11 I
b1 *
b1 D
b1 J
b11101 /
b11101 E
b11101 K
b1111111 N
b100011 L
b11111111111111111111111111111101 9
b11111111111111111111111111111101 R
b11111111111111111111111111111101 b
b11111110001100001000111010100011 8
b11111110001100001000111010100011 M
b11111110001100001000111010100011 v
b10 ;
b10 w
b1000 >
b1000 l
b1000 u
b1000 t
1"
#85
0"
#90
1.
b101 \
b101 ^
b101 ]
b101 _
b101 '
b101 B
b101 e
b101 n
b101 4
b101 `
b101 j
b101 U
b101 :
b101 Y
b101 f
13
1+
b0 =
b0 P
b0 W
b0 q
11
02
b11111111111111111111111111111101 @
b11111111111111111111111111111101 o
b0 (
b0 a
b0 c
b0 Z
b0 [
b0 ?
b0 p
b11101 g
b11111111111111111111111111111101 h
b11101 )
b11101 C
b11101 I
b100 /
b100 E
b100 K
b11 L
b11111111111111111111111111111101 9
b11111111111111111111111111111101 R
b11111111111111111111111111111101 b
b111111100100 S
b0 V
b0 ,
b0 G
b0 X
b0 -
b0 F
b0 d
b11111111110100001000001000000011 8
b11111111110100001000001000000011 M
b11111111110100001000001000000011 v
b11 ;
b11 w
b1100 >
b1100 l
b1100 u
b1100 t
b100000 H
1"
#95
0"
#100
b10000 ?
b10000 p
b0 4
b0 `
b0 j
b0 '
b0 B
b0 e
b0 n
b0 <
b0 k
b0 r
17
10
b100100 =
b100100 P
b100100 W
b100100 q
11
03
1+
b111111111111111110000 T
b10001 g
b11111111111111111111111111110001 h
b11111111111111111111111111110000 @
b11111111111111111111111111110000 o
b10001 )
b10001 C
b10001 I
b11111 *
b11111 D
b11111 J
b10 /
b10 E
b10 K
b111 O
b1101111 L
b11111111111111111111111111110000 9
b11111111111111111111111111110000 R
b11111111111111111111111111110000 b
b11111111000111111111000101101111 8
b11111111000111111111000101101111 M
b11111111000111111111000101101111 v
b100 ;
b100 w
b10000 >
b10000 l
b10000 u
b10000 t
1"
#105
0"
#110
b0 Z
b0 [
b0 4
b0 `
b0 j
b0 V
b0 ,
b0 G
b0 X
b0 -
b0 F
b0 d
07
b101 =
b101 P
b101 W
b101 q
00
11
1+
b101 @
b101 o
b101 <
b101 k
b101 r
b101 )
b101 C
b101 I
b0 *
b0 D
b0 J
b11 /
b11 E
b11 K
b0 N
b0 O
b10011 L
b101 9
b101 R
b101 b
bx0 T
b0 ?
b0 p
b10100000000000110010011 8
b10100000000000110010011 M
b10100000000000110010011 v
b0 ;
b0 w
b0 >
b0 l
b0 u
15
b101 '
b101 B
b101 e
b101 n
b0 t
1"
#115
0"
#120
b10 '
b10 B
b10 e
b10 n
b10 <
b10 k
b10 r
b10 @
b10 o
b10 )
b10 C
b10 I
b1 /
b1 E
b1 K
b10 9
b10 R
b10 b
b1000000000000010010011 8
b1000000000000010010011 M
b1000000000000010010011 v
b1 ;
b1 w
b100 >
b100 l
b100 u
b100 t
05
1"
#125
0"
#130
0.
b101 (
b101 a
b101 c
b0 '
b0 B
b0 e
b0 n
b101 Z
b101 [
b101 ?
b101 p
b11101 g
b11111111111111111111111111111101 h
b0 <
b0 k
b0 r
b101 V
b101 ,
b101 G
b101 X
b10 -
b10 F
b10 d
12
b1111 =
b1111 P
b1111 W
b1111 q
11
0+
b111111111101 S
b11111111111111111111111111111101 @
b11111111111111111111111111111101 o
b11 )
b11 C
b11 I
b1 *
b1 D
b1 J
b11101 /
b11101 E
b11101 K
b1111111 N
b100011 L
b11111111111111111111111111111101 9
b11111111111111111111111111111101 R
b11111111111111111111111111111101 b
b11111110001100001000111010100011 8
b11111110001100001000111010100011 M
b11111110001100001000111010100011 v
b10 ;
b10 w
b1000 >
b1000 l
b1000 u
b1000 t
1"
#135
0"
#140
1.
b101 \
b101 ^
b101 ]
b101 _
b101 '
b101 B
b101 e
b101 n
b101 4
b101 `
b101 j
b101 U
b101 :
b101 Y
b101 f
13
1+
b0 =
b0 P
b0 W
b0 q
11
02
b11111111111111111111111111111101 @
b11111111111111111111111111111101 o
b0 (
b0 a
b0 c
b0 Z
b0 [
b0 ?
b0 p
b11101 g
b11111111111111111111111111111101 h
b11101 )
b11101 C
b11101 I
b100 /
b100 E
b100 K
b11 L
b11111111111111111111111111111101 9
b11111111111111111111111111111101 R
b11111111111111111111111111111101 b
b111111100100 S
b0 V
b0 ,
b0 G
b0 X
b0 -
b0 F
b0 d
b11111111110100001000001000000011 8
b11111111110100001000001000000011 M
b11111111110100001000001000000011 v
b11 ;
b11 w
b1100 >
b1100 l
b1100 u
b1100 t
b100000 H
1"
#145
0"
#150
b10000 ?
b10000 p
b0 4
b0 `
b0 j
b0 '
b0 B
b0 e
b0 n
b0 <
b0 k
b0 r
17
10
b100100 =
b100100 P
b100100 W
b100100 q
11
03
1+
b111111111111111110000 T
b10001 g
b11111111111111111111111111110001 h
b11111111111111111111111111110000 @
b11111111111111111111111111110000 o
b10001 )
b10001 C
b10001 I
b11111 *
b11111 D
b11111 J
b10 /
b10 E
b10 K
b111 O
b1101111 L
b11111111111111111111111111110000 9
b11111111111111111111111111110000 R
b11111111111111111111111111110000 b
b11111111000111111111000101101111 8
b11111111000111111111000101101111 M
b11111111000111111111000101101111 v
b100 ;
b100 w
b10000 >
b10000 l
b10000 u
b10000 t
1"
#155
0"
#160
b0 Z
b0 [
b0 4
b0 `
b0 j
b0 V
b0 ,
b0 G
b0 X
b0 -
b0 F
b0 d
07
b101 =
b101 P
b101 W
b101 q
00
11
1+
b101 @
b101 o
b101 <
b101 k
b101 r
b101 )
b101 C
b101 I
b0 *
b0 D
b0 J
b11 /
b11 E
b11 K
b0 N
b0 O
b10011 L
b101 9
b101 R
b101 b
bx0 T
b0 ?
b0 p
b10100000000000110010011 8
b10100000000000110010011 M
b10100000000000110010011 v
b0 ;
b0 w
b0 >
b0 l
b0 u
15
b101 '
b101 B
b101 e
b101 n
b0 t
1"
#165
0"
#170
b10 '
b10 B
b10 e
b10 n
b10 <
b10 k
b10 r
b10 @
b10 o
b10 )
b10 C
b10 I
b1 /
b1 E
b1 K
b10 9
b10 R
b10 b
b1000000000000010010011 8
b1000000000000010010011 M
b1000000000000010010011 v
b1 ;
b1 w
b100 >
b100 l
b100 u
b100 t
05
1"
#175
0"
