single_cycle_dev/verilog_zaid/main/src/data_mem_intf.v
module DMI(
    input wire [31:0]load,
    input wire [5:0]aluOP,
    input wire [31:0] rs2,
    output reg [31:0]load_data,
    output reg [31:0]store_data
);
localparam loadByte = 6'd0;
localparam loadHalf = 6'd1;
localparam loadByteUnsigned = 6'd3;
localparam loadHalfUnsigned = 6'd4;
localparam loadWord = 6'd2;
localparam storeWord = 6'd17;
localparam storeHalf = 6'd16;
localparam storeByte = 6'd15;

wire [7:0]LB;
wire [15:0]LH;
wire [7:0]LBU;
wire [15:0]LHU;
wire [31:0]LW;

wire [31:0] SW;
wire [15:0] SH;
wire [7:0] SB;

assign LB = load[7:0];
assign LH = load[15:0];
assign LBU = load[7:0];
assign LHU = load[15:0];
assign LW = load[31:0];

assign SW = rs2;
assign SH = rs2[15:0];
assign SB = rs2[7:0];

always @(*) begin
    case(aluOP)
    loadByte: begin
        load_data = $signed({{24{LB[7]}},LB}); // load bite
    end
    loadHalf: begin
        load_data = $signed({{16{LH[15]}},LH}); // load half bite
    end
    loadByteUnsigned: begin
        load_data = $unsigned({24'b0,LBU}); //load bite unsigned
    end
    loadHalfUnsigned: begin
        load_data = $unsigned({16'b0, LHU}); //load halfword unsigned 
    end
    loadWord: begin
        load_data = LW; //load word remains same 
    end
    storeWord: begin
        store_data = SW;     // store word 
    end
    storeHalf: begin
        store_data = $unsigned({16'b0, SH});    // store half word 
    end
    storeByte: begin
        store_data = $unsigned({24'b0, SB});    // store byte
    end
    default: begin
    load_data = 32'b0;
    store_data = 32'b0;
    end
    endcase
end

endmodule

single_cycle_dev/verilog_zaid/main/src/RAM.v
module RAM (
    input wire clk,
    input wire [31:0] StoreData,
    input wire [31:0] LoadData,
    input wire [31:0] rs1,
    input wire [31:0] Immediate,
    input wire readWrite,   
    output reg [31:0] dataOUT
);
    reg [31:0] RAM [0:31]; // 32 words of memory
    wire [31:0] loc;
    assign loc = rs1 + Immediate;
    wire [4:0] address;
    assign address = loc [4:0];

    always @(posedge clk) begin
        if (readWrite) begin
            dataOUT <= RAM[address];
        end 
        else if (~readWrite) begin
            RAM[address] <= dataIN; // Write
        end

    end
endmodule

single_cycle_dev/verilog_zaid/main/src/alu.v
module alu(
  input wire [31:0]a,
  input wire [31:0]b,
  input wire [5:0]opcode,
  output reg [31:0]c
);

  always @(*) begin
        case(opcode) 
        6'd5: c = a + b;
        6'd6: c = a << b;
        6'd7: c = ($signed(a) < $signed(b)) ? 32'b1 : 32'b0;
        6'd8: c = ($unsigned(a) < $unsigned(b) ) ? 32'b1 : 32'b0;
        6'd9: c = a ^ b;
        6'd10: c = a >> b;
        6'd11: c = a >>> b;
        6'd12: c = a | b;
        6'd13: c = a & b;
        6'd18: c = a + b;
        6'd19: c = a - b;
        6'd20: c = a << b;
        6'd21: c = ($unsigned(a) < $unsigned(b)) ? 32'b1 : 32'b0;
        6'd22: c = ($unsigned(a) < $unsigned(b)) ? 32'b1 : 32'b0;
        6'd23: c = a ^ b; 
        6'd24: c = a >> b; 
        6'd25: c = a >>> b; 
        6'd26: c = a | b;
        6'd27: c = a & b;
        default: c = 32'b0;
        endcase
  end
endmodule

single_cycle_dev/verilog_zaid/main/src/registerfile.v
module register (
    input wire clk,
    input wire reset,
    input wire regWrite, 
    input [31:0] write_data,
    input [4:0] rd_data,
    input [4:0] rs1_data,
    input [4:0] rs2_data,
    output reg [31:0] read_data1,
    output reg [31:0] read_data2
);
    reg [31:0] registerf [0:31];
    integer i;

    // Synchronous
    always @(posedge clk) begin
        if (reset || ~regWrite) begin
            for (i = 0; i < 32; i = i + 1) 
                registerf[i] <= 32'b0; 
        end else if (regWrite && rd_data != 0) begin
            registerf[rd_data] <= write_data; 
        end
    end

    // ASynchronous
    always @(*) begin
        read_data1 = (rs1_data == 0) ? 32'b0 : registerf[rs1_data];
        read_data2 = (rs2_data == 0) ? 32'b0 : registerf[rs2_data];
    end

endmodule

single_cycle_dev/verilog_zaid/main/src/control_decode.v
module ControlDecoder(
    input wire [31:0] instruction,
    output reg [31:0] imm_gen_inst,
    output wire [4:0] rs1,
    output wire [4:0] rs2,
    output wire [4:0] rd,
    output reg regWrite,
    output reg memToReg,
    output reg memWrite,
    output reg operandA,
    output reg operandB,
    output reg branch,
    output reg [5:0] aluOP,
    output reg jalrEN,
    output reg jalEN
);

localparam load_Itype = 7'b0000011;
localparam alu_Itype = 7'b0010011;
localparam jalr_Itype = 7'b1100111;
localparam alu_rtype = 7'b0110011; 

// instr decode
wire [6:0] opcode = instruction[6:0];
wire [2:0] func3 = instruction[14:12];
wire [6:0] func7 = instruction[31:25];
assign rd = instruction[11:7];
assign rs1 = instruction[19:15];
assign rs2 = instruction[24:20];

// Immediate generation logic
always @(*) begin
    case (opcode)
        load_Itype, alu_Itype, jalr_Itype: begin
            imm_gen_inst = {{20{instruction[31]}}, instruction[31:20]};  //Sign extension
        end
        default: begin
            imm_gen_inst = 32'b0;
        end
    endcase
end

// Control decode logic
always @(*) begin
    regWrite = 0;
    memToReg = 0;
    memWrite = 0;
    operandA = 0;
    operandB = 0;
    branch = 0;
    aluOP = 6'd0;
    jalrEN = 0;
    jalEN = 0;

    case (opcode)
        alu_rtype: begin
            case (func3)
                3'd0: aluOP = func7[5] ? 6'd19 : 6'd18;  // SUB or ADD
                3'd1: aluOP = 6'd20;  // SLL
                3'd2: aluOP = 6'd21;  // SLT
                3'd3: aluOP = 6'd22;  // SLTU
                3'd4: aluOP = 6'd23;  // XOR
                3'd5: aluOP = func7[5] ? 6'd25 : 6'd24;  // SRA or SRL
                3'd6: aluOP = 6'd26;  // OR
                3'd7: aluOP = 6'd27;  // AND
            endcase
            regWrite = 1;
        end
        alu_Itype: begin
            case (func3)
                3'd0: aluOP = 6'd5;   // ADDI
                3'd1: aluOP = 6'd6;   // SLLI
                3'd2: aluOP = 6'd7;   // SLTI
                3'd3: aluOP = 6'd8;   // SLTIU
                3'd4: aluOP = 6'd9;   // XORI
                3'd5: aluOP = func7[5] ? 6'd11 : 6'd10;  // SRAI or SRLI
                3'd6: aluOP = 6'd12;  // ORI
                3'd7: aluOP = 6'd13;  // ANDI
            endcase
            regWrite = 1;
            operandA = 1;
        end
        load_Itype: begin
            case (func3)
                3'd0: aluOP = 6'd0;  // LB
                3'd1: aluOP = 6'd1;  // LH
                3'd2: aluOP = 6'd2;  // LW
                3'd3: aluOP = 6'd3;  // LD
                3'd4: aluOP = 6'd4;  // LBU
            endcase
            regWrite = 1;
            memToReg = 1;
            operandA = 1;
        end
        jalr_Itype: begin
            aluOP = 6'd35;  // JALR operation
            regWrite = 1;
            operandA = 1;
        end
    endcase
end

endmodule

single_cycle_dev/verilog_zaid/main/src/fetch.v
module fetch(
    input wire clk,
    input wire rst,
    input wire en,
    output reg [31:0] counterOUT,  
    output reg [4:0] mem_address,  
    output reg [31:0] instruction       
);

    reg [31:0] PC;  
    reg [31:0] INST_MEM [0:31];  

    initial begin
        $readmemh("file.mem", INST_MEM);
    end

    always @(posedge clk or posedge en) begin
        if (rst) begin
            PC = 32'd0;
        end
        else begin
            PC = PC + 32'd4; 
        end

        counterOUT = PC;
        mem_address = PC[6:2];  
        instruction = INST_MEM[mem_address];
    end

endmodule

single_cycle_dev/verilog_zaid/main/src/main.v
module MAIN (
    input wire clk,
    input [31:0] dataIN,
    input wire rst,
    input wire en,
    input wire RW
);
    // Internal Wires
    wire [4:0] counter_address;
    wire [31:0] imm_gen_inst;
    wire [4:0] rs1, rs2, rd;
    wire regWrite, memToReg, memWrite, readWrite , operandA, operandB;
    wire branch, jalrEN, jalEN;
    wire [5:0] aluOP;
    wire [31:0] write_data, read_data1, read_data2;
    wire [31:0] aluOut, PC, instMemOUT, dataMemLoad, load_write , store_data;

    // Fetch Stage
    fetch u_fetch(
        .clk(clk),
        .rst(rst),
        .en(en),
        .counterOUT(PC),
        .mem_address(counter_address),
        .instruction(instMemOUT)
    );

    // Control Decoder
    ControlDecoder u_ControlDecode (
        .instruction(instMemOUT),
        .imm_gen_inst(imm_gen_inst),
        .rs1(rs1),
        .rs2(rs2),
        .rd(rd),
        .regWrite(regWrite),
        .memToReg(memToReg),
        .memWrite(memWrite),
        .operandA(operandA),
        .operandB(operandB),
        .aluOP(aluOP)
    );

    // Register File
    register o_register (
        .clk(clk),
        .reset(rst),
        .regWrite(regWrite),
        .write_data(write_data),
        .rd_data(rd),
        .rs1_data(rs1),
        .rs2_data(rs2),
        .read_data1(read_data1),
        .read_data2(read_data2)
    );
    wire [31:0] OpA;
    wire [31:0] OpB;
    assign OpA = operandA ? imm_gen_inst : read_data1;
    assign OpB = operandB ? PC  : read_data2;
    assign readWrite = (memToReg) ? 1 : (memWrite) ? 0 : -1;
    // ALU
    alu u_alu (
        .a(OpA),
        .b(OpB),
        .opcode(aluOP),
        .c(aluOut)
    );

    // Data Memory (RAM2)
    RAM u_RAM2 (
        .clk(clk),
        .rs1(read_data1),
        .StoreData(store_data),
        .LoadData(load_write),
        .Immediate(imm_gen_inst),
        .readWrite(readWrite), 
        .dataIN(load_write),   
        .dataOUT(dataMemLoad)
    );

    // Data Memory Interface (DMI)
    DMI u_DMI (
        .load(dataMemLoad),
        .rs2(read_data2),
        .store_data(store_data),
        .aluOP(aluOP),
        .load_data(load_write)
    );

    // Write Back
    assign write_data = memToReg ? load_write : aluOut;
endmodule

single_cycle_dev/verilog_zaid/main/tb/main_tb.v
module MAIN_tb();
    reg clk;
    reg [31:0]dataIN;
    reg rst;
    reg en;
    reg RW;


always begin
    #5 clk = ~clk;
end

MAIN u_MAIN(
    .clk(clk),
    .dataIN(dataIN),
    .rst(rst),
    .en(en),
    .RW(RW)
);


initial begin
    clk = 1;
    rst = 0;
    en = 0;
    #10 rst = 1;
    #5 rst = 0;
    #50 en = 0;
    #100 $finish;
end


initial begin
    $dumpfile("temp/main.vcd");
    $dumpvars(0,MAIN_tb); 
end


endmodule

single_cycle_dev/verilog_zaid/main/temp/main.vcd
$date
	Tue Dec  3 17:33:41 2024
$end
$version
	Icarus Verilog
$end
$timescale
	1s
$end
$scope module MAIN_tb $end
$var reg 1 ! RW $end
$var reg 1 " clk $end
$var reg 32 # dataIN [31:0] $end
$var reg 1 $ en $end
$var reg 1 % rst $end
$scope module u_MAIN $end
$var wire 1 ! RW $end
$var wire 1 " clk $end
$var wire 32 & dataIN [31:0] $end
$var wire 1 $ en $end
$var wire 1 % rst $end
$var wire 32 ' write_data [31:0] $end
$var wire 32 ( store_data [31:0] $end
$var wire 5 ) rs2 [4:0] $end
$var wire 5 * rs1 [4:0] $end
$var wire 1 + regWrite $end
$var wire 32 , read_data2 [31:0] $end
$var wire 32 - read_data1 [31:0] $end
$var wire 1 . readWrite $end
$var wire 5 / rd [4:0] $end
$var wire 1 0 operandB $end
$var wire 1 1 operandA $end
$var wire 1 2 memWrite $end
$var wire 1 3 memToReg $end
$var wire 32 4 load_write [31:0] $end
$var wire 32 5 instMemOUT [31:0] $end
$var wire 32 6 imm_gen_inst [31:0] $end
$var wire 32 7 dataMemLoad [31:0] $end
$var wire 5 8 counter_address [4:0] $end
$var wire 32 9 aluOut [31:0] $end
$var wire 6 : aluOP [5:0] $end
$var wire 32 ; PC [31:0] $end
$var wire 32 < OpB [31:0] $end
$var wire 32 = OpA [31:0] $end
$scope module o_register $end
$var wire 1 " clk $end
$var wire 1 % reset $end
$var wire 32 > write_data [31:0] $end
$var wire 5 ? rs2_data [4:0] $end
$var wire 5 @ rs1_data [4:0] $end
$var wire 1 + regWrite $end
$var wire 5 A rd_data [4:0] $end
$var reg 32 B read_data1 [31:0] $end
$var reg 32 C read_data2 [31:0] $end
$var integer 32 D i [31:0] $end
$upscope $end
$scope module u_ControlDecode $end
$var wire 5 E rs2 [4:0] $end
$var wire 5 F rs1 [4:0] $end
$var wire 5 G rd [4:0] $end
$var wire 7 H opcode [6:0] $end
$var wire 32 I instruction [31:0] $end
$var wire 7 J func7 [6:0] $end
$var wire 3 K func3 [2:0] $end
$var reg 6 L aluOP [5:0] $end
$var reg 1 M branch $end
$var reg 32 N imm_gen_inst [31:0] $end
$var reg 1 O jalEN $end
$var reg 1 P jalrEN $end
$var reg 1 3 memToReg $end
$var reg 1 2 memWrite $end
$var reg 1 1 operandA $end
$var reg 1 0 operandB $end
$var reg 1 + regWrite $end
$upscope $end
$scope module u_DMI $end
$var wire 32 Q LW [31:0] $end
$var wire 32 R SW [31:0] $end
$var wire 6 S aluOP [5:0] $end
$var wire 32 T rs2 [31:0] $end
$var wire 32 U load [31:0] $end
$var wire 16 V SH [15:0] $end
$var wire 8 W SB [7:0] $end
$var wire 16 X LHU [15:0] $end
$var wire 16 Y LH [15:0] $end
$var wire 8 Z LBU [7:0] $end
$var wire 8 [ LB [7:0] $end
$var reg 32 \ load_data [31:0] $end
$var reg 32 ] store_data [31:0] $end
$upscope $end
$scope module u_RAM2 $end
$var wire 32 ^ Immediate [31:0] $end
$var wire 1 " clk $end
$var wire 32 _ dataIN [31:0] $end
$var wire 1 . readWrite $end
$var wire 32 ` rs1 [31:0] $end
$var wire 32 a loc [31:0] $end
$var wire 5 b address [4:0] $end
$var reg 32 c dataOUT [31:0] $end
$upscope $end
$scope module u_alu $end
$var wire 32 d a [31:0] $end
$var wire 32 e b [31:0] $end
$var wire 6 f opcode [5:0] $end
$var reg 32 g c [31:0] $end
$upscope $end
$scope module u_fetch $end
$var wire 1 " clk $end
$var wire 1 $ en $end
$var wire 1 % rst $end
$var reg 32 h PC [31:0] $end
$var reg 32 i counterOUT [31:0] $end
$var reg 32 j instruction [31:0] $end
$var reg 5 k mem_address [4:0] $end
$upscope $end
$upscope $end
$upscope $end
$enddefinitions $end
#0
$dumpvars
bx k
bx j
bx i
bx h
bx g
bx f
bx e
bx d
bx c
bx b
bx a
bx `
bx _
bx ^
bx ]
bx \
bx [
bx Z
bx Y
bx X
bx W
bx V
bx U
bx T
bx S
bx R
bx Q
xP
xO
bx N
xM
bx L
bx K
bx J
bx I
bx H
bx G
bx F
bx E
bx D
bx C
bx B
bx A
bx @
bx ?
bx >
bx =
bx <
bx ;
bx :
bx 9
bx 8
bx 7
bx 6
bx 5
bx 4
x3
x2
x1
x0
bx /
x.
bx -
bx ,
x+
bx *
bx )
bx (
bx '
bx &
0%
0$
bx #
1"
x!
$end
#5
0"
#10
b100 '
b100 >
b100 9
b100 g
b0 V
b0 W
b0 <
b0 e
b0 R
b0 ,
b0 C
b0 T
1.
b100 b
b0 (
b0 ]
b0 4
b0 \
b0 _
b100 =
b100 d
b100 a
b0 -
b0 B
b0 `
0O
0P
b101 :
b101 L
b101 S
b101 f
0M
00
11
02
03
1+
b100 )
b100 ?
b100 E
b0 *
b0 @
b0 F
b1 /
b1 A
b1 G
b0 J
b0 K
b10011 H
b100 6
b100 N
b100 ^
b100000 D
b10000000000000010010011 5
b10000000000000010010011 I
b10000000000000010010011 j
b0 8
b0 k
b0 ;
b0 i
b0 h
1"
1%
#15
0"
0%
#20
b101 '
b101 >
b101 9
b101 g
b101 b
b101 =
b101 d
b101 )
b101 ?
b101 E
b10 /
b10 A
b10 G
b101 a
b101 6
b101 N
b101 ^
b10100000000000100010011 5
b10100000000000100010011 I
b10100000000000100010011 j
b1 8
b1 k
b100 ;
b100 i
b100 h
1"
#25
0"
#30
bx '
bx >
bx 4
bx \
bx _
b0 9
b0 g
13
b10 :
b10 L
b10 S
b10 f
11
1+
b11 *
b11 @
b11 F
b100 /
b100 A
b100 G
b10 K
b11 H
b10100011010001000000011 5
b10100011010001000000011 I
b10100011010001000000011 j
b10 8
b10 k
b1000 ;
b1000 i
b1000 h
1"
#35
0"
#40
b101 V
b101 W
b101 <
b101 e
b0 4
b0 \
b0 _
b1 '
b1 >
b1 9
b1 g
b101 R
b101 ,
b101 C
b101 T
b100 -
b100 B
b100 `
b10111 :
b10111 L
b10111 S
b10111 f
01
03
1+
b100 b
b100 =
b100 d
b10 )
b10 ?
b10 E
b1 *
b1 @
b1 F
b110 /
b110 A
b110 G
b100 K
b110011 H
b100 a
b0 6
b0 N
b0 ^
b1000001100001100110011 5
b1000001100001100110011 I
b1000001100001100110011 j
b11 8
b11 k
b1100 ;
b1100 i
b1100 h
1"
#45
0"
#50
0.
b0 '
b0 >
b100 V
b100 W
b100 <
b100 e
b0 =
b0 d
b100 (
b100 ]
b0 9
b0 g
b100 R
b100 ,
b100 C
b100 T
11
12
b10001 :
b10001 L
b10001 S
b10001 f
0+
b1 )
b1 ?
b1 E
b11 /
b11 A
b11 G
b10 K
b100011 H
b100001010000110100011 5
b100001010000110100011 I
b100001010000110100011 j
b100 8
b100 k
b10000 ;
b10000 i
b10000 h
1"
#55
0"
#60
1.
bx V
bx W
bx <
bx e
bx b
bx 4
bx \
bx _
bx =
bx d
bx R
bx ,
bx C
bx T
bx a
bx -
bx B
bx `
b0 :
b0 L
b0 S
b0 f
01
02
bx )
bx ?
bx E
bx *
bx @
bx F
bx /
bx A
bx G
bx J
bx K
bx H
b100000 D
bx 5
bx I
bx j
b101 8
b101 k
b10100 ;
b10100 i
b10100 h
1"
#65
0"
#70
b100000 D
b110 8
b110 k
b11000 ;
b11000 i
b11000 h
1"
#75
0"
#80
b100000 D
b111 8
b111 k
b11100 ;
b11100 i
b11100 h
1"
#85
0"
#90
b100000 D
b1000 8
b1000 k
b100000 ;
b100000 i
b100000 h
1"
#95
0"
#100
b100000 D
b1001 8
b1001 k
b100100 ;
b100100 i
b100100 h
1"
#105
0"
#110
b100000 D
b1010 8
b1010 k
b101000 ;
b101000 i
b101000 h
1"
#115
0"
#120
b100000 D
b1011 8
b1011 k
b101100 ;
b101100 i
b101100 h
1"
#125
0"
#130
b100000 D
b1100 8
b1100 k
b110000 ;
b110000 i
b110000 h
1"
#135
0"
#140
b100000 D
b1101 8
b1101 k
b110100 ;
b110100 i
b110100 h
1"
#145
0"
#150
b100000 D
b1110 8
b1110 k
b111000 ;
b111000 i
b111000 h
1"
#155
0"
#160
b100000 D
b1111 8
b1111 k
b111100 ;
b111100 i
b111100 h
1"
