single_cycle_dev/verilog_zaid/main/src/writeBack.v
module WriteBack (
    input wire clk,
    input wire [31:0] load_write,
    input wire [31:0] PC_in,
    input wire [31:0] aluOut,
    input wire [31:0] imm_gen_inst,
    input wire memToReg,
    input wire jalEN,
    input wire jalrEN,
    input wire branchEN,
    output reg [31:0] write_data,
    output reg [31:0] PC_out,
    output reg jump
);
    always @(posedge clk) begin
        jump = 0;
        if ( jalEN || jalrEN ) begin
            write_data <= PC_in + 4;
            PC_out <= aluOut; 
            jump <= 1;
        end
        else if (branchEN) begin
            PC_out <= (aluOut [0] == 1) ? PC_in + imm_gen_inst : PC_in + 4;
            jump <= 1; 
        end
    end

    always @(*) begin
        if (memToReg) begin
            write_data = load_write;
        end
        else if(~branchEN) begin
                write_data = aluOut;
            end
        end
endmodule

single_cycle_dev/verilog_zaid/main/src/data_mem_intf.v
module DMI(
    input wire [31:0]load,
    input wire [5:0]aluOP,
    input wire [31:0] rs2,
    output reg [31:0]load_data,
    output reg [31:0]store_data
);
localparam loadByte = 6'd0;
localparam loadHalf = 6'd1;
localparam loadByteUnsigned = 6'd3;
localparam loadHalfUnsigned = 6'd4;
localparam loadWord = 6'd2;
localparam storeWord = 6'd17;
localparam storeHalf = 6'd16;
localparam storeByte = 6'd15;

wire [7:0]LB;
wire [15:0]LH;
wire [7:0]LBU;
wire [15:0]LHU;
wire [31:0]LW;

wire [31:0] SW;
wire [15:0] SH;
wire [7:0] SB;

assign LB = load[7:0];
assign LH = load[15:0];
assign LBU = load[7:0];
assign LHU = load[15:0];
assign LW = load[31:0];

assign SW = rs2;
assign SH = rs2[15:0];
assign SB = rs2[7:0];

always @(*) begin
    case(aluOP)
    loadByte: begin
        load_data = $signed({{24{LB[7]}},LB}); // load bite
    end
    loadHalf: begin
        load_data = $signed({{16{LH[15]}},LH}); // load half bite
    end
    loadByteUnsigned: begin
        load_data = $unsigned({24'b0,LBU}); //load bite unsigned
    end
    loadHalfUnsigned: begin
        load_data = $unsigned({16'b0, LHU}); //load halfword unsigned 
    end
    loadWord: begin
        load_data = LW; //load word remains same 
    end
    storeWord: begin
        store_data = SW;     // store word 
    end
    storeHalf: begin
        store_data = $unsigned({16'b0, SH});    // store half word 
    end
    storeByte: begin
        store_data = $unsigned({24'b0, SB});    // store byte
    end
    default: begin
    load_data = 32'b0;
    store_data = 32'b0;
    end
    endcase
end

endmodule

five_stage_pipeline_dev/verilog_zaid/main/src/RAM.v
module RAM (
    input wire clk,
    input wire [31:0] MemWrite,
    input wire [31:0] rs1,
    input wire [31:0] rd,
    input wire [31:0] Immediate,
    input wire memToReg,
    input wire memWrite,   
    output reg [31:0] MemRead
);
    reg [31:0] RAM [0:31]; 

    reg [31:0] loc;
    reg [4:0] address;

    integer i;

    initial begin
        for (i = 0; i < 32; i = i + 1) begin
        RAM[i] = 32'd0;
    end
    end

    always @(*) begin
    if (memToReg) begin             
            loc = rs1 + Immediate;
            address = loc [4:0];
    end
    else if (memWrite) begin
            loc = rd + Immediate;
            address = loc [4:0];
    end
    end

    always @(posedge clk) begin
        if (memToReg) begin              //readWrite true -> Read and false -> Write
            MemRead <= RAM[address];

        end 
        else if (memWrite) begin
            RAM[address] <= MemWrite;
        end
    end
    always @(*) begin
    if (memToReg) begin
        MemRead = RAM[address];
    end
end


endmodule

single_cycle_dev/verilog_zaid/main/src/alu.v
module alu(
  input wire [31:0]a,
  input wire [31:0]b,
  input wire [5:0]opcode,
  output reg [31:0]c
);

  always @(*) begin
        case(opcode) 
        6'd5: c = a + b;
        6'd6: c = a << b;
        6'd7: c = ($signed(a) < $signed(b)) ? 32'b1 : 32'b0;
        6'd8: c = ($unsigned(a) < $unsigned(b) ) ? 32'b1 : 32'b0;
        6'd9: c = a ^ b;
        6'd10: c = a >> b;
        6'd11: c = a >>> b;
        6'd12: c = a | b;
        6'd13: c = a & b;
        6'd18: c = a + b;
        6'd19: c = a - b;
        6'd20: c = a << b;
        6'd21: c = ($unsigned(a) < $unsigned(b)) ? 32'b1 : 32'b0;
        6'd22: c = ($unsigned(a) < $unsigned(b)) ? 32'b1 : 32'b0;
        6'd23: c = a ^ b; 
        6'd24: c = a >> b; 
        6'd25: c = a >>> b; 
        6'd26: c = a | b;
        6'd27: c = a & b;
        default: c = 32'b0;
        endcase
  end
endmodule

single_cycle_dev/verilog_zaid/main/src/registerfile.v
module register (
    input wire clk,
    input wire reset,
    input wire regWrite, 
    input [31:0] write_data,
    input [4:0] rd_data,
    input [4:0] rs1_data,
    input [4:0] rs2_data,
    output reg [31:0] read_data1,
    output reg [31:0] read_data2
);
    reg [31:0] registerf [0:31];
    integer i;

    // Synchronous
    always @(posedge clk) begin
        if (reset || ~regWrite) begin
            for (i = 0; i < 32; i = i + 1) 
                registerf[i] <= 32'b0; 
        end else if (regWrite && rd_data != 0) begin
            registerf[rd_data] <= write_data; 
        end
    end

    // ASynchronous
    always @(*) begin
        read_data1 = (rs1_data == 0) ? 32'b0 : registerf[rs1_data];
        read_data2 = (rs2_data == 0) ? 32'b0 : registerf[rs2_data];
    end

endmodule

single_cycle_dev/verilog_zaid/main/src/control_decode.v
module ControlDecoder(
    input wire [31:0] instruction,
    output reg [31:0] imm_gen_inst,
    output wire [4:0] rs1,
    output wire [4:0] rs2,
    output wire [4:0] rd,
    output reg regWrite,
    output reg memToReg,
    output reg memWrite,
    output reg operandA,
    output reg operandB,
    output reg branch,
    output reg [5:0] aluOP,
    output reg jalrEN,
    output reg jalEN,
    output reg branchEN
);

localparam load_Itype = 7'b0000011;
localparam alu_Itype = 7'b0010011;
localparam jalr_Itype = 7'b1100111;
localparam alu_rtype = 7'b0110011; 
localparam store = 7'b0100011; //0100011

// instr decode
wire [6:0] opcode = instruction[6:0];
wire [2:0] func3 = instruction[14:12];
wire [6:0] func7 = instruction[31:25];
reg [11:0] split_inst;
reg [20:0] split_inst2;
reg [12:0] split_inst3;

assign rd = (~branchEN) ? instruction[11:7] : -5'd1;
assign rs1 = instruction[19:15];
assign rs2 = instruction[24:20];

// Immediate generation logic
always @(*) begin
    case (opcode)
        load_Itype, alu_Itype, jalr_Itype: begin
            imm_gen_inst = {{20{instruction[31]}}, instruction[31:20]};  //laod , alu_i-type and jalr_i-type
        end
        7'd35: begin   
            split_inst [4:0] = instruction [11:7];
            split_inst [11:5] = instruction [31:25];                                                   //store instruction 
            imm_gen_inst = {{20{split_inst[11]}}, split_inst};
        end
        7'd23 , 7'd55: begin                                //auipc and lui U-type
            imm_gen_inst = {instruction[31:12], 12'b0};
        end
        7'd111: begin                               //jal-UJ
            split_inst2 [0] = 1'b0;
            split_inst2 [20] = instruction [31];
            split_inst2 [11] = instruction [20];
            split_inst2 [10:1] = instruction [30:21];
            split_inst2 [19:12] = instruction [19:12];
            imm_gen_inst = {{11{split_inst2[20]}}, split_inst2};
        end
        7'd99: begin                        //branch SB-type
            split_inst3 [0] = 1'b0;
            split_inst3 [4:1] = instruction [11:8];
            split_inst3 [10:5] = instruction [30:25];
            split_inst3 [11] = instruction [7];
            split_inst3 [12] = instruction [31];
            imm_gen_inst = {{19{split_inst3[12]}}, split_inst3};
        end
        default: begin
            imm_gen_inst = 32'b0;
        end
    endcase
end

// Control decode logic
always @(*) begin
    regWrite = 0;
    memToReg = 0;
    memWrite = 0;
    operandA = 0;
    operandB = 0;
    branch = 0;
    aluOP = 6'd0;
    branchEN = 0;
    jalrEN = 0;
    jalEN = 0;

    case (opcode)
        alu_rtype: begin
            case (func3)
                3'd0: aluOP = func7[5] ? 6'd19 : 6'd18;  // SUB or ADD
                3'd1: aluOP = 6'd20;  // SLL
                3'd2: aluOP = 6'd21;  // SLT
                3'd3: aluOP = 6'd22;  // SLTU
                3'd4: aluOP = 6'd23;  // XOR
                3'd5: aluOP = func7[5] ? 6'd25 : 6'd24;  // SRA or SRL
                3'd6: aluOP = 6'd26;  // OR
                3'd7: aluOP = 6'd27;  // AND
            endcase
            regWrite = 1;
        end
        alu_Itype: begin
            case (func3)
                3'd0: aluOP = 6'd5;   // ADDI
                3'd1: aluOP = 6'd6;   // SLLI
                3'd2: aluOP = 6'd7;   // SLTI
                3'd3: aluOP = 6'd8;   // SLTIU
                3'd4: aluOP = 6'd9;   // XORI
                3'd5: aluOP = func7[5] ? 6'd11 : 6'd10;  // SRAI or SRLI
                3'd6: aluOP = 6'd12;  // ORI
                3'd7: aluOP = 6'd13;  // ANDI
            endcase
            regWrite = 1;
            operandA = 1;
        end
        load_Itype: begin
            case (func3)
                3'd0: aluOP = 6'd0;  // LB
                3'd1: aluOP = 6'd1;  // LH
                3'd2: aluOP = 6'd2;  // LW
                3'd3: aluOP = 6'd3;  // LD
                3'd4: aluOP = 6'd4;  // LBU
            endcase
            regWrite = 1;
            memToReg = 1;
            operandA = 1;
        end
        jalr_Itype: begin
            aluOP = 6'd35;  // JALR operation
            regWrite = 1;
            operandA = 1;
            jalrEN = 1;
        end
        7'd35: begin
            case(func3)
                3'd0: aluOP = 6'd15;  // SB
                3'd1: aluOP = 6'd16;  // SH
                3'd2: aluOP = 6'd17;  // SW
            endcase
                memWrite = 1;
                operandA = 1;
        end
        7'd23: begin        //AUIPC
            aluOP = 6'd14;
            regWrite = 1;
            operandA = 1;
            operandB = 1;
        end
        7'd55: begin        //LUI
            aluOP = 6'd28;
            regWrite = 1;
            operandA = 1;
        end 
        7'd111: begin       //jal
            aluOP = 6'd36;
            regWrite = 1;
            operandA = 1;
            operandB = 1;
            jalEN = 1;
        end
        7'd99: begin
            case (func3)
                3'd0: aluOP = 6'd29;
                3'd1: aluOP = 6'd30;
                3'd2: aluOP = 6'd31;
                3'd3: aluOP = 6'd32;
                3'd4: aluOP = 6'd33;
                3'd5: aluOP = 6'd34; 
            endcase
            branchEN = 1;
        end
    endcase
end

endmodule

single_cycle_dev/verilog_zaid/main/src/fetch.v
module fetch(
    input wire clk,
    input wire rst,
    input wire en,
    input wire jump,
    input wire [31:0] JPC,
    output reg [31:0] counterOUT,  
    output reg [4:0] mem_address,  
    output reg [31:0] instruction       
);

    reg [31:0] FPC;  
    reg [31:0] INST_MEM [0:31];  
    
    initial begin
        $readmemh("file.mem", INST_MEM);
    end

    always @(*) begin
    if (~jump) begin
        FPC = counterOUT;
    end else begin
        FPC = JPC;
    end
    end

    always @(posedge clk or posedge rst) begin
        if (rst) begin
            FPC <= 32'd0; // Reset PC to zero
        end else if (en) begin
            FPC <= FPC + 32'd4; // Increment PC by 4 when enabled
        end
    end

    always @(*) begin
        counterOUT = FPC;
        mem_address = FPC[6:2];  // Word-aligned memory address
        instruction = INST_MEM[mem_address];
    end

endmodule

single_cycle_dev/verilog_zaid/main/src/main.v
module MAIN (
    input wire clk,
    input [31:0] dataIN,
    input wire rst,
    input wire en
);
    // Internal Wires
    wire [4:0] counter_address;
    wire [31:0] imm_gen_inst;
    wire [4:0] rs1, rs2, rd;
    wire regWrite, memToReg, memWrite, readWrite , operandA, operandB;
    wire branch, jalrEN, jalEN , jump , branchEN;
    wire [5:0] aluOP;
    wire [31:0] write_data, read_data1, read_data2;
    wire [31:0] aluOut, PC, JPC , instMemOUT, dataMemLoad, load_write , store_data;

    // Fetch Stage
    fetch u_fetch(
        .clk(clk),
        .rst(rst),
        .en(en),
        .JPC(JPC),
        .counterOUT(PC),
        .mem_address(counter_address),
        .instruction(instMemOUT),
        .jump(jump)
    );

    // Control Decoder
    ControlDecoder u_ControlDecode (
        .instruction(instMemOUT),
        .imm_gen_inst(imm_gen_inst),
        .rs1(rs1),
        .rs2(rs2),
        .rd(rd),
        .regWrite(regWrite),
        .memToReg(memToReg),
        .memWrite(memWrite),
        .operandA(operandA),
        .operandB(operandB),
        .aluOP(aluOP),
        .jalrEN(jalrEN),
        .jalEN(jalEN),
        .branchEN(branchEN)
    );

    // Register File
    register o_register (
        .clk(clk),
        .reset(rst),
        .regWrite(regWrite),
        .write_data(write_data),
        .rd_data(rd),
        .rs1_data(rs1),
        .rs2_data(rs2),
        .read_data1(read_data1),
        .read_data2(read_data2)
    );
    wire [31:0] OpA;
    wire [31:0] OpB;
    assign OpA = operandA ? imm_gen_inst : read_data1;
    assign OpB = operandB ? PC  : read_data2;
    assign readWrite = (memToReg) ? 1 : (memWrite) ? 0 : -1;
    // ALU
    alu u_alu (
        .a(OpA),
        .b(OpB),
        .opcode(aluOP),
        .c(aluOut)
    );

    // Data Memory (RAM2)
    RAM u_RAM2 (
        .clk(clk),
        .rs1(read_data1),
        .rd(write_data),
        .Immediate(imm_gen_inst),
        .memToReg(memToReg),
        .memWrite(memWrite),
        .MemWrite(store_data),  
        .MemRead(dataMemLoad)
    );

    // Data Memory Interface (DMI)
    DMI u_DMI (
        .load(dataMemLoad),
        .rs2(read_data2),
        .store_data(store_data),
        .aluOP(aluOP),
        .load_data(load_write)
    );

    WriteBack u_WriteBack (
    .clk(clk),
    .load_write(load_write),
    .PC_in(PC),
    .aluOut(aluOut),
    .memToReg(memToReg),
    .jalEN(jalEN),
    .jalrEN(jalrEN),
    .imm_gen_inst(imm_gen_inst),
    .write_data(write_data),
    .PC_out(JPC),
    .jump(jump),
    .branchEN(branchEN)
);

endmodule

single_cycle_dev/verilog_zaid/main/tb/main_tb.v
module MAIN_tb();
    reg clk;
    reg [31:0]dataIN;
    reg rst;
    reg en;


always begin
    #5 clk = ~clk;
end

MAIN u_MAIN(
    .clk(clk),
    .dataIN(dataIN),
    .rst(rst),
    .en(en)
);


initial begin
    clk = 1;
    rst = 1;
    #5 rst = 0;
    en = 1;
    #10 rst = 1;
    #5 rst = 0;
    #190 en = 0;
    #200 $finish;
end


initial begin
    $dumpfile("temp/main.vcd");
    $dumpvars(0,MAIN_tb); 
end


endmodule

single_cycle_dev/verilog_zaid/main/temp/main.vcd
$date
	Sun Dec  8 21:45:07 2024
$end
$version
	Icarus Verilog
$end
$timescale
	1s
$end
$scope module MAIN_tb $end
$var reg 1 ! clk $end
$var reg 32 " dataIN [31:0] $end
$var reg 1 # en $end
$var reg 1 $ rst $end
$scope module u_MAIN $end
$var wire 1 ! clk $end
$var wire 32 % dataIN [31:0] $end
$var wire 1 # en $end
$var wire 1 $ rst $end
$var wire 32 & write_data [31:0] $end
$var wire 32 ' store_data [31:0] $end
$var wire 5 ( rs2 [4:0] $end
$var wire 5 ) rs1 [4:0] $end
$var wire 1 * regWrite $end
$var wire 32 + read_data2 [31:0] $end
$var wire 32 , read_data1 [31:0] $end
$var wire 1 - readWrite $end
$var wire 5 . rd [4:0] $end
$var wire 1 / operandB $end
$var wire 1 0 operandA $end
$var wire 1 1 memWrite $end
$var wire 1 2 memToReg $end
$var wire 32 3 load_write [31:0] $end
$var wire 1 4 jump $end
$var wire 1 5 jalrEN $end
$var wire 1 6 jalEN $end
$var wire 32 7 instMemOUT [31:0] $end
$var wire 32 8 imm_gen_inst [31:0] $end
$var wire 32 9 dataMemLoad [31:0] $end
$var wire 5 : counter_address [4:0] $end
$var wire 1 ; branchEN $end
$var wire 32 < aluOut [31:0] $end
$var wire 6 = aluOP [5:0] $end
$var wire 32 > PC [31:0] $end
$var wire 32 ? OpB [31:0] $end
$var wire 32 @ OpA [31:0] $end
$var wire 32 A JPC [31:0] $end
$scope module o_register $end
$var wire 1 ! clk $end
$var wire 1 $ reset $end
$var wire 32 B write_data [31:0] $end
$var wire 5 C rs2_data [4:0] $end
$var wire 5 D rs1_data [4:0] $end
$var wire 1 * regWrite $end
$var wire 5 E rd_data [4:0] $end
$var reg 32 F read_data1 [31:0] $end
$var reg 32 G read_data2 [31:0] $end
$var integer 32 H i [31:0] $end
$upscope $end
$scope module u_ControlDecode $end
$var wire 5 I rs2 [4:0] $end
$var wire 5 J rs1 [4:0] $end
$var wire 5 K rd [4:0] $end
$var wire 7 L opcode [6:0] $end
$var wire 32 M instruction [31:0] $end
$var wire 7 N func7 [6:0] $end
$var wire 3 O func3 [2:0] $end
$var reg 6 P aluOP [5:0] $end
$var reg 1 Q branch $end
$var reg 1 ; branchEN $end
$var reg 32 R imm_gen_inst [31:0] $end
$var reg 1 6 jalEN $end
$var reg 1 5 jalrEN $end
$var reg 1 2 memToReg $end
$var reg 1 1 memWrite $end
$var reg 1 0 operandA $end
$var reg 1 / operandB $end
$var reg 1 * regWrite $end
$var reg 12 S split_inst [11:0] $end
$var reg 21 T split_inst2 [20:0] $end
$var reg 13 U split_inst3 [12:0] $end
$upscope $end
$scope module u_DMI $end
$var wire 32 V LW [31:0] $end
$var wire 32 W SW [31:0] $end
$var wire 6 X aluOP [5:0] $end
$var wire 32 Y rs2 [31:0] $end
$var wire 32 Z load [31:0] $end
$var wire 16 [ SH [15:0] $end
$var wire 8 \ SB [7:0] $end
$var wire 16 ] LHU [15:0] $end
$var wire 16 ^ LH [15:0] $end
$var wire 8 _ LBU [7:0] $end
$var wire 8 ` LB [7:0] $end
$var reg 32 a load_data [31:0] $end
$var reg 32 b store_data [31:0] $end
$upscope $end
$scope module u_RAM2 $end
$var wire 32 c Immediate [31:0] $end
$var wire 32 d MemWrite [31:0] $end
$var wire 1 ! clk $end
$var wire 1 2 memToReg $end
$var wire 1 1 memWrite $end
$var wire 32 e rs1 [31:0] $end
$var wire 32 f rd [31:0] $end
$var reg 32 g MemRead [31:0] $end
$var reg 5 h address [4:0] $end
$var reg 32 i loc [31:0] $end
$var integer 32 j i [31:0] $end
$upscope $end
$scope module u_WriteBack $end
$var wire 1 ; branchEN $end
$var wire 1 ! clk $end
$var wire 32 k imm_gen_inst [31:0] $end
$var wire 1 6 jalEN $end
$var wire 1 5 jalrEN $end
$var wire 32 l load_write [31:0] $end
$var wire 1 2 memToReg $end
$var wire 32 m aluOut [31:0] $end
$var wire 32 n PC_in [31:0] $end
$var reg 32 o PC_out [31:0] $end
$var reg 1 4 jump $end
$var reg 32 p write_data [31:0] $end
$upscope $end
$scope module u_alu $end
$var wire 32 q a [31:0] $end
$var wire 32 r b [31:0] $end
$var wire 6 s opcode [5:0] $end
$var reg 32 t c [31:0] $end
$upscope $end
$scope module u_fetch $end
$var wire 32 u JPC [31:0] $end
$var wire 1 ! clk $end
$var wire 1 # en $end
$var wire 1 4 jump $end
$var wire 1 $ rst $end
$var reg 32 v FPC [31:0] $end
$var reg 32 w counterOUT [31:0] $end
$var reg 32 x instruction [31:0] $end
$var reg 5 y mem_address [4:0] $end
$upscope $end
$upscope $end
$upscope $end
$enddefinitions $end
#0
$dumpvars
b0 y
b10100000000000110010011 x
b0 w
b0 v
bx u
b101 t
b101 s
b0 r
b101 q
b101 p
bx o
b0 n
b101 m
b0 l
b101 k
b100000 j
bx i
bx h
bx g
b101 f
b0 e
b0 d
b101 c
b0 b
b0 a
bx `
bx _
bx ^
bx ]
b0 \
b0 [
bx Z
b0 Y
b101 X
b0 W
bx V
bx U
bx T
bx S
b101 R
0Q
b101 P
b0 O
b0 N
b10100000000000110010011 M
b10011 L
b11 K
b0 J
b101 I
b100000 H
b0 G
b0 F
b11 E
b0 D
b101 C
b101 B
bx A
b101 @
b0 ?
b0 >
b101 =
b101 <
0;
b0 :
bx 9
b101 8
b10100000000000110010011 7
06
05
04
b0 3
02
01
10
0/
b11 .
1-
b0 ,
b0 +
1*
b0 )
b101 (
b0 '
b101 &
bx %
1$
x#
bx "
1!
$end
#5
1#
0$
0!
#10
b10 &
b10 B
b10 f
b10 p
b10 <
b10 m
b10 t
b1 .
b1 E
b1 K
b10 @
b10 q
b10 (
b10 C
b10 I
b10 8
b10 R
b10 c
b10 k
b1000000000000010010011 7
b1000000000000010010011 M
b1000000000000010010011 x
b1 :
b1 y
b100 >
b100 n
b100 w
b100 v
1!
#15
b101 &
b101 B
b101 f
b101 p
b101 <
b101 m
b101 t
b11 .
b11 E
b11 K
b101 @
b101 q
b101 (
b101 C
b101 I
b101 8
b101 R
b101 c
b101 k
b10100000000000110010011 7
b10100000000000110010011 M
b10100000000000110010011 x
b0 :
b0 y
b0 >
b0 n
b0 w
b0 v
0!
1$
#20
b10 &
b10 B
b10 f
b10 p
b10 <
b10 m
b10 t
b1 .
b1 E
b1 K
b10 @
b10 q
b10 (
b10 C
b10 I
b10 8
b10 R
b10 c
b10 k
b1000000000000010010011 7
b1000000000000010010011 M
b1000000000000010010011 x
b1 :
b1 y
b100 >
b100 n
b100 w
b100 v
1!
0$
#25
0!
#30
b100000000001000 &
b100000000001000 B
b100000000001000 f
b100000000001000 p
b1000 ?
b1000 r
b100000000001000 <
b100000000001000 m
b100000000001000 t
1/
b1110 =
b1110 P
b1110 X
b1110 s
10
1*
b100000000000000 @
b100000000000000 q
b0 (
b0 C
b0 I
b100 O
b10111 L
b100000000000000 8
b100000000000000 R
b100000000000000 c
b100000000000000 k
b100000010010111 7
b100000010010111 M
b100000010010111 x
b10 :
b10 y
b1000 >
b1000 n
b1000 w
b1000 v
1!
#35
0!
#40
0-
b101 '
b101 b
b101 d
b101 [
b101 \
b11101 h
b11111111111111111111111111111101 i
b0 &
b0 B
b0 f
b0 p
b101 W
b101 +
b101 G
b101 Y
b100000000001000 ,
b100000000001000 F
b100000000001000 e
b11101 .
b11101 E
b11101 K
11
b1111 =
b1111 P
b1111 X
b1111 s
0/
10
0*
b111111111101 S
b11111111111111111111111111111101 @
b11111111111111111111111111111101 q
b0 <
b0 m
b0 t
b11 (
b11 C
b11 I
b1 )
b1 D
b1 J
b1111111 N
b0 O
b100011 L
b11111111111111111111111111111101 8
b11111111111111111111111111111101 R
b11111111111111111111111111111101 c
b11111111111111111111111111111101 k
b101 ?
b101 r
b11111110001100001000111010100011 7
b11111110001100001000111010100011 M
b11111110001100001000111010100011 x
b11 :
b11 y
b1100 >
b1100 n
b1100 w
b1100 v
1!
#45
0!
#50
1-
b101 ]
b101 _
b101 ^
b101 `
b101 &
b101 B
b101 f
b101 p
b101 3
b101 a
b101 l
b101 V
b101 9
b101 Z
b101 g
b100 .
b100 E
b100 K
12
1*
b0 =
b0 P
b0 X
b0 s
10
01
b11111111111111111111111111111101 @
b11111111111111111111111111111101 q
b0 '
b0 b
b0 d
b0 [
b0 \
b0 ?
b0 r
b11101 h
b11111111111111111111111111111101 i
b11101 (
b11101 C
b11101 I
b11 L
b11111111111111111111111111111101 8
b11111111111111111111111111111101 R
b11111111111111111111111111111101 c
b11111111111111111111111111111101 k
b111111100100 S
b0 W
b0 +
b0 G
b0 Y
b0 ,
b0 F
b0 e
b11111111110100001000001000000011 7
b11111111110100001000001000000011 M
b11111111110100001000001000000011 x
b100 :
b100 y
b10000 >
b10000 n
b10000 w
b10000 v
b100000 H
1!
#55
0!
#60
b0 3
b0 a
b0 l
b11111 .
b11111 E
b11111 K
1;
b100001 =
b100001 P
b100001 X
b100001 s
00
02
0*
b1111111110100 U
b11 h
b11111111111111111111111111100011 i
b0 @
b0 q
b11 (
b11 C
b11 I
b100 O
b1100011 L
b11111111111111111111111111110100 8
b11111111111111111111111111110100 R
b11111111111111111111111111110100 c
b11111111111111111111111111110100 k
b11111110001100001100101011100011 7
b11111110001100001100101011100011 M
b11111110001100001100101011100011 x
b101 :
b101 y
b10100 >
b10100 n
b10100 w
b10100 v
1!
#65
0!
#70
b1 <
b1 m
b1 t
1;
b100010 =
b100010 P
b100010 X
b100010 s
b0 N
b101 O
b1000 8
b1000 R
b1000 c
b1000 k
b1000 U
b1100001101010001100011 7
b1100001101010001100011 M
b1100001101010001100011 x
b110 :
b110 y
b11000 >
b11000 n
b11000 w
14
b11000 A
b11000 o
b11000 u
b11000 v
b100000 H
1!
#75
0!
#80
b100000 ?
b100000 r
b10 .
b10 E
b10 K
16
1/
b111111111111111100000 T
b11111111111111111111111111100000 @
b11111111111111111111111111100000 q
b0 &
b0 B
b0 f
b0 p
b0 <
b0 m
b0 t
b1111111 N
10
1*
0;
b100100 =
b100100 P
b100100 X
b100100 s
b1 (
b1 C
b1 I
b11111 )
b11111 D
b11111 J
b111 O
b1101111 L
b11111111111111111111111111100000 8
b11111111111111111111111111100000 R
b11111111111111111111111111100000 c
b11111111111111111111111111100000 k
b100000000100 U
b11111110000111111111000101101111 7
b11111110000111111111000101101111 M
b11111110000111111111000101101111 x
b1000 :
b1000 y
b100000 >
b100000 n
b100000 w
b100000 A
b100000 o
b100000 u
b100000 v
b100000 H
14
1!
#85
0!
#90
b0 [
b0 \
b0 3
b0 a
b0 l
b0 W
b0 +
b0 G
b0 Y
b0 ,
b0 F
b0 e
b11 .
b11 E
b11 K
06
b101 =
b101 P
b101 X
b101 s
0/
10
1*
b101 @
b101 q
b101 <
b101 m
b101 t
b101 (
b101 C
b101 I
b0 )
b0 D
b0 J
b0 N
b0 O
b10011 L
b101 8
b101 R
b101 c
b101 k
bx0 T
b0 ?
b0 r
b10100000000000110010011 7
b10100000000000110010011 M
b10100000000000110010011 x
b0 :
b0 y
b0 >
b0 n
b0 w
b0 A
b0 o
b0 u
b101 &
b101 B
b101 f
b101 p
b0 v
14
1!
#95
0!
#100
b10 &
b10 B
b10 f
b10 p
b10 <
b10 m
b10 t
b1 .
b1 E
b1 K
b10 @
b10 q
b10 (
b10 C
b10 I
b10 8
b10 R
b10 c
b10 k
b1000000000000010010011 7
b1000000000000010010011 M
b1000000000000010010011 x
b1 :
b1 y
b100 >
b100 n
b100 w
b100 v
04
1!
#105
0!
#110
b100000000001000 &
b100000000001000 B
b100000000001000 f
b100000000001000 p
b1000 ?
b1000 r
b100000000001000 <
b100000000001000 m
b100000000001000 t
1/
b1110 =
b1110 P
b1110 X
b1110 s
10
1*
b100000000000000 @
b100000000000000 q
b0 (
b0 C
b0 I
b100 O
b10111 L
b100000000000000 8
b100000000000000 R
b100000000000000 c
b100000000000000 k
b100000010010111 7
b100000010010111 M
b100000010010111 x
b10 :
b10 y
b1000 >
b1000 n
b1000 w
b1000 v
1!
#115
0!
#120
0-
b101 '
b101 b
b101 d
b101 [
b101 \
b11101 h
b11111111111111111111111111111101 i
b0 &
b0 B
b0 f
b0 p
b101 W
b101 +
b101 G
b101 Y
b100000000001000 ,
b100000000001000 F
b100000000001000 e
b11101 .
b11101 E
b11101 K
11
b1111 =
b1111 P
b1111 X
b1111 s
0/
10
0*
b111111111101 S
b11111111111111111111111111111101 @
b11111111111111111111111111111101 q
b0 <
b0 m
b0 t
b11 (
b11 C
b11 I
b1 )
b1 D
b1 J
b1111111 N
b0 O
b100011 L
b11111111111111111111111111111101 8
b11111111111111111111111111111101 R
b11111111111111111111111111111101 c
b11111111111111111111111111111101 k
b101 ?
b101 r
b11111110001100001000111010100011 7
b11111110001100001000111010100011 M
b11111110001100001000111010100011 x
b11 :
b11 y
b1100 >
b1100 n
b1100 w
b1100 v
1!
#125
0!
#130
1-
b101 ]
b101 _
b101 ^
b101 `
b101 &
b101 B
b101 f
b101 p
b101 3
b101 a
b101 l
b101 V
b101 9
b101 Z
b101 g
b100 .
b100 E
b100 K
12
1*
b0 =
b0 P
b0 X
b0 s
10
01
b11111111111111111111111111111101 @
b11111111111111111111111111111101 q
b0 '
b0 b
b0 d
b0 [
b0 \
b0 ?
b0 r
b11101 h
b11111111111111111111111111111101 i
b11101 (
b11101 C
b11101 I
b11 L
b11111111111111111111111111111101 8
b11111111111111111111111111111101 R
b11111111111111111111111111111101 c
b11111111111111111111111111111101 k
b111111100100 S
b0 W
b0 +
b0 G
b0 Y
b0 ,
b0 F
b0 e
b11111111110100001000001000000011 7
b11111111110100001000001000000011 M
b11111111110100001000001000000011 x
b100 :
b100 y
b10000 >
b10000 n
b10000 w
b10000 v
b100000 H
1!
#135
0!
#140
b0 3
b0 a
b0 l
b11111 .
b11111 E
b11111 K
1;
b100001 =
b100001 P
b100001 X
b100001 s
00
02
0*
b1111111110100 U
b11 h
b11111111111111111111111111100011 i
b0 @
b0 q
b11 (
b11 C
b11 I
b100 O
b1100011 L
b11111111111111111111111111110100 8
b11111111111111111111111111110100 R
b11111111111111111111111111110100 c
b11111111111111111111111111110100 k
b11111110001100001100101011100011 7
b11111110001100001100101011100011 M
b11111110001100001100101011100011 x
b101 :
b101 y
b10100 >
b10100 n
b10100 w
b10100 v
1!
#145
0!
#150
b1 <
b1 m
b1 t
1;
b100010 =
b100010 P
b100010 X
b100010 s
b0 N
b101 O
b1000 8
b1000 R
b1000 c
b1000 k
b1000 U
b1100001101010001100011 7
b1100001101010001100011 M
b1100001101010001100011 x
b110 :
b110 y
b11000 >
b11000 n
b11000 w
14
b11000 A
b11000 o
b11000 u
b11000 v
b100000 H
1!
#155
0!
#160
b100000 ?
b100000 r
b10 .
b10 E
b10 K
16
1/
b111111111111111100000 T
b11111111111111111111111111100000 @
b11111111111111111111111111100000 q
b0 &
b0 B
b0 f
b0 p
b0 <
b0 m
b0 t
b1111111 N
10
1*
0;
b100100 =
b100100 P
b100100 X
b100100 s
b1 (
b1 C
b1 I
b11111 )
b11111 D
b11111 J
b111 O
b1101111 L
b11111111111111111111111111100000 8
b11111111111111111111111111100000 R
b11111111111111111111111111100000 c
b11111111111111111111111111100000 k
b100000000100 U
b11111110000111111111000101101111 7
b11111110000111111111000101101111 M
b11111110000111111111000101101111 x
b1000 :
b1000 y
b100000 >
b100000 n
b100000 w
b100000 A
b100000 o
b100000 u
b100000 v
b100000 H
14
1!
#165
0!
