single_cycle_dev/verilog_zaid/main/src/registerfile.v
module register(
    input wire clk,
    input wire enable,
    input wire reset,
    input [31:0] write_data,
    input [4:0] rd_data,
    input [4:0] rs1_data,
    input [4:0] rs2_data,
    output wire [31:0] read_data1,
    output wire [31:0] read_data2
);
reg [31:0] registerf [0:31];
integer i;
always @(posedge clk) begin
    if(reset) begin
        for(i=0; i<32; i++)
        registerf[i]=0;
    end
    else begin
        if(enable) registerf[rd_data] <= write_data;
    end
end

assign read_data1 = (rs1_data == 0) ? 32'b0 : registerf[rs1_data];
assign read_data2 = (rs2_data == 0) ? 32'b0 : registerf[rs2_data];

endmodule

single_cycle_dev/verilog_zaid/main/tb/reg_tb.v
module register_tb;
    reg clk;
    reg enable;
    reg reset;
    reg [31:0] write_data;
    reg [4:0] rd_data;
    reg [4:0] rs1_data;
    reg [4:0] rs2_data;
    wire [31:0] read_data1;
    wire [31:0] read_data2;

    register u_register (
        .clk(clk),
        .enable(enable),
        .reset(reset),
        .write_data(write_data),
        .rd_data(rd_data),
        .rs1_data(rs1_data),
        .rs2_data(rs2_data),
        .read_data1(read_data1),
        .read_data2(read_data2)
    );

    always #5 clk = ~clk;

    initial begin
        clk = 0;
        reset = 1;
        enable = 0;
        write_data = 32'b0;
        rd_data = 5'b0;
        rs1_data = 5'b0;
        rs2_data = 5'b0;
        rs2_data = 5'd1;

        #10 reset = 0;
        #10 enable = 1;
        rd_data = 5'd1;
        write_data = 32'hDEAD;

        #10 rd_data = 5'd1;

        #10 enable = 1;
        reset = 1;
        #10 reset = 0;

        #10 rs1_data = 5'd1;
        #50;
        $finish;
    end

initial begin
    $dumpfile("./temp/reg.vcd");
    $dumpvars(0,register_tb);    
end

endmodule

single_cycle_dev/verilog_zaid/main/temp/reg.vcd
$date
	Fri Nov 29 21:05:56 2024
$end
$version
	Icarus Verilog
$end
$timescale
	1s
$end
$scope module register_tb $end
$var wire 32 ! read_data2 [31:0] $end
$var wire 32 " read_data1 [31:0] $end
$var reg 1 # clk $end
$var reg 1 $ enable $end
$var reg 5 % rd_data [4:0] $end
$var reg 1 & reset $end
$var reg 5 ' rs1_data [4:0] $end
$var reg 5 ( rs2_data [4:0] $end
$var reg 32 ) write_data [31:0] $end
$scope module u_register $end
$var wire 1 # clk $end
$var wire 1 $ enable $end
$var wire 5 * rd_data [4:0] $end
$var wire 1 & reset $end
$var wire 5 + rs1_data [4:0] $end
$var wire 5 , rs2_data [4:0] $end
$var wire 32 - write_data [31:0] $end
$var wire 32 . read_data2 [31:0] $end
$var wire 32 / read_data1 [31:0] $end
$var integer 32 0 i [31:0] $end
$upscope $end
$upscope $end
$enddefinitions $end
#0
$dumpvars
bx 0
b0 /
bx .
b0 -
b1 ,
b0 +
b0 *
b0 )
b1 (
b0 '
1&
b0 %
0$
0#
b0 "
bx !
$end
#5
b0 !
b0 .
b100000 0
1#
#10
0#
0&
#15
1#
#20
0#
b1101111010101101 )
b1101111010101101 -
b1 %
b1 *
1$
#25
b1101111010101101 !
b1101111010101101 .
1#
#30
0#
#35
1#
#40
0#
1&
#45
b0 !
b0 .
b100000 0
1#
#50
0#
0&
#55
b1101111010101101 !
b1101111010101101 .
1#
#60
b1101111010101101 "
b1101111010101101 /
0#
b1 '
b1 +
