verilog_practice_tasks/comb-seq/register_file/src/register.v
module register(
    input wire clk,
    input wire enable,
    input wire reset,
    input [31:0] write_data,
    input [4:0] rd_data,
    input [4:0] rs1_data,
    input [4:0] rs2_data,
    output wire [32:0] read_data1,
    output wire [32:0] read_data2
);

//sequential section
reg [31:0] registerf [0:31];
integer i;
always @(posedge clk) begin
    if(reset) begin
        for(i=0; i<32; i++)
        registerf[i]<=0;
    end
    else begin
        if(enable) registerf[rd_data] <= write_data;
    end
end

//combination section
assign read_data1 = (rs1_data == 0) ? 32'b0 : registerf[rs1_data];
assign read_data2 = (rs2_data == 0) ? 32'b0 : registerf[rs2_data];

endmodule

verilog_practice_tasks/Sequential/register_file/tb/register_tb.v
module register_tb();
    reg clk;
    reg enable;
    reg reset;
    reg [31:0] write_data;
    reg [4:0] rd_data;
    reg [4:0] rs1_data;
    reg [4:0] rs2_data;
    wire [32:0] read_data1;
    wire [32:0] read_data2;

register u_register(
    .clk(clk),
    .reset(reset),
    .enable(enable),
    .write_data(write_data),
    .rd_data(rd_data),
    .rs1_data(rs1_data),
    .rs2_data(rs2_data),
    .read_data1(read_data1),
    .read_data2(read_data2)
);

always begin
    #5 clk = ~clk;
end

initial begin
    clk = 0;
    enable = 0;
    reset = 0;
    #5;
    reset = 1;
    enable = 0;
    #5;
    enable = 1;
    reset = 0;
    write_data = 32'd435;
    rd_data = 5'd8;
    rs1_data = 5'd8;
    rs2_data = 5'd9;
    #70;
    reset = 1;
    enable = 0;
    #100;
    $finish;
end

initial begin
    $dumpfile("temp/register.vcd");
    $dumpvars(0,register_tb);
end

endmodule

verilog_practice_tasks/comb-seq/register_file/temp/register.vcd
$date
	Fri Sep 27 17:47:13 2024
$end
$version
	Icarus Verilog
$end
$timescale
	1s
$end
$scope module register_tb $end
$var wire 33 ! read_data2 [32:0] $end
$var wire 33 " read_data1 [32:0] $end
$var reg 1 # clk $end
$var reg 1 $ enable $end
$var reg 5 % rd_data [4:0] $end
$var reg 1 & reset $end
$var reg 5 ' rs1_data [4:0] $end
$var reg 5 ( rs2_data [4:0] $end
$var reg 32 ) write_data [31:0] $end
$scope module u_register $end
$var wire 1 # clk $end
$var wire 1 $ enable $end
$var wire 5 * rd_data [4:0] $end
$var wire 1 & reset $end
$var wire 5 + rs1_data [4:0] $end
$var wire 5 , rs2_data [4:0] $end
$var wire 32 - write_data [31:0] $end
$var wire 33 . read_data2 [32:0] $end
$var wire 33 / read_data1 [32:0] $end
$var integer 32 0 i [31:0] $end
$upscope $end
$upscope $end
$enddefinitions $end
#0
$dumpvars
bx 0
b0xxxxxxxxxxxxxxxxxxxxxxxxxxxxxxxx /
b0xxxxxxxxxxxxxxxxxxxxxxxxxxxxxxxx .
bx -
bx ,
bx +
bx *
bx )
bx (
bx '
0&
bx %
0$
0#
b0xxxxxxxxxxxxxxxxxxxxxxxxxxxxxxxx "
b0xxxxxxxxxxxxxxxxxxxxxxxxxxxxxxxx !
$end
#5
b100000 0
1&
1#
#10
b0 !
b0 .
b0 "
b0 /
b1001 (
b1001 ,
b1000 '
b1000 +
b1000 %
b1000 *
b110110011 )
b110110011 -
0&
1$
0#
#15
b110110011 "
b110110011 /
1#
#20
0#
#25
1#
#30
0#
#35
1#
#40
0#
#45
1#
#50
0#
#55
1#
#60
0#
#65
1#
#70
0#
#75
1#
#80
0#
0$
1&
#85
b0 "
b0 /
b100000 0
1#
#90
0#
#95
b100000 0
1#
#100
0#
#105
b100000 0
1#
#110
0#
#115
b100000 0
1#
#120
0#
#125
b100000 0
1#
#130
0#
#135
b100000 0
1#
#140
0#
#145
b100000 0
1#
#150
0#
#155
b100000 0
1#
#160
0#
#165
b100000 0
1#
#170
0#
#175
b100000 0
1#
